Workbook

Sheet Proyectos de Venta V2
A1: GESTIÓN DE PROYECTOS DE VENTA · Argentina
A2: Actualizado: 21/05/2026 | 🔵 Inputs en azul | ⚫ Fórmulas en negro | 🟢 Resultados clave | MK variable — recomendado 46%
A3: ⚙ PARÁMETROS — Argentina 2025
A4: DÓLAR | B4: 1550 | C4: IVA (%) | D4: 0.21 | E4: MK (%) | F4: 0.4 | G4: MK MÍNIMO (%) | H4: 0.3 | I4: COMISION (%) | J4: 0.05
A5: INFLACIÓN ANUAL | B5: 0.3 | C5: IMPREVISTOS (%) | D5: 0.1 | E5: CUOTA (Meses) | F5: 12 | G5: CANT. AÑOS PROY. | H5: 0 | I5: COMODATO %
A6: N° | B6: PRODUCTO / SERVICIO | C6: PROVEEDOR | D6: ESTADO | E6: CANT. | F6: COSTO USD | G6: COSTO ARS | H6: IMPREVISTOS | I6: COSTO REAL SIN IVA | J6: MK (%) | K6: COMISION | L6: P. VENTA SIN IVA | M6: P. VENTA CON IVA | N6: UTILIDAD ARS
A7: 1 | B7: PRUEBAS | E7: 1 | F7: 10000 | G7: =IF(F7=0,0,F7*$B$4*E7) -> 15500000 | H7: =IF(F7=0,0,G7*$D$5) -> 1550000 | I7: =IF(F7=0,0,G7+H7) -> 17050000 | J7: =$F$4 -> 0.4 | K7: =IF(F7=0,0,I7*$J$4) -> 852500 | L7: =IF(F7=0,0,I7*(1+$J$7)+K7) -> 24722500 | M7: =IF(F7=0,0,L7*(1+$D$4)) -> 29914225 | N7: =IF(F7=0,0,L7-I7) -> 7672500
A8: 2 | B8: PRUEBA 2 | E8: 100 | F8: 2 | G8: =IF(F8=0,0,F8*$B$4*E8) -> 310000 | H8: =IF(F8=0,0,G8*$D$5) -> 31000 | I8: =IF(F8=0,0,G8+H8) -> 341000 | J8: =$F$4 -> 0.4 | K8: =IF(F8=0,0,I8*$J$4) -> 17050 | L8: =IF(F8=0,0,I8*(1+$J$7)+K8) -> 494450 | M8: =IF(F8=0,0,L8*(1+$D$4)) -> 598284.5 | N8: =IF(F8=0,0,L8-I8) -> 153450
A9: 3 | E9: 0 | F9: 0 | G9: =IF(F9=0,0,F9*$B$4*E9) -> 0 | H9: =IF(F9=0,0,G9*$D$5) -> 0 | I9: =IF(F9=0,0,G9+H9) -> 0 | J9: =$F$4 -> 0.4 | K9: =IF(F9=0,0,I9*$J$4) -> 0 | L9: =IF(F9=0,0,I9*(1+$J$7)+K9) -> 0 | M9: =IF(F9=0,0,L9*(1+$D$4)) -> 0 | N9: =IF(F9=0,0,L9-I9) -> 0
A10: 4 | E10: 0 | F10: 0 | G10: =IF(F10=0,0,F10*$B$4*E10) -> 0 | H10: =IF(F10=0,0,G10*$D$5) -> 0 | I10: =IF(F10=0,0,G10+H10) -> 0 | J10: =$F$4 -> 0.4 | K10: =IF(F10=0,0,I10*$J$4) -> 0 | L10: =IF(F10=0,0,I10*(1+$J$7)+K10) -> 0 | M10: =IF(F10=0,0,L10*(1+$D$4)) -> 0 | N10: =IF(F10=0,0,L10-I10) -> 0
A11: 5 | E11: 0 | F11: 0 | G11: =IF(F11=0,0,F11*$B$4*E11) -> 0 | H11: =IF(F11=0,0,G11*$D$5) -> 0 | I11: =IF(F11=0,0,G11+H11) -> 0 | J11: =$F$4 -> 0.4 | K11: =IF(F11=0,0,I11*$J$4) -> 0 | L11: =IF(F11=0,0,I11*(1+$J$7)+K11) -> 0 | M11: =IF(F11=0,0,L11*(1+$D$4)) -> 0 | N11: =IF(F11=0,0,L11-I11) -> 0
A12: 6 | E12: 0 | F12: 0 | G12: =IF(F12=0,0,F12*$B$4*E12) -> 0 | H12: =IF(F12=0,0,G12*$D$5) -> 0 | I12: =IF(F12=0,0,G12+H12) -> 0 | J12: =$F$4 -> 0.4 | K12: =IF(F12=0,0,I12*$J$4) -> 0 | L12: =IF(F12=0,0,I12*(1+$J$7)+K12) -> 0 | M12: =IF(F12=0,0,L12*(1+$D$4)) -> 0 | N12: =IF(F12=0,0,L12-I12) -> 0
A13: 7 | E13: 0 | F13: 0 | G13: =IF(F13=0,0,F13*$B$4*E13) -> 0 | H13: =IF(F13=0,0,G13*$D$5) -> 0 | I13: =IF(F13=0,0,G13+H13) -> 0 | J13: =$F$4 -> 0.4 | K13: =IF(F13=0,0,I13*$J$4) -> 0 | L13: =IF(F13=0,0,I13*(1+$J$7)+K13) -> 0 | M13: =IF(F13=0,0,L13*(1+$D$4)) -> 0 | N13: =IF(F13=0,0,L13-I13) -> 0
A14: 8 | E14: 0 | F14: 0 | G14: =IF(F14=0,0,F14*$B$4*E14) -> 0 | H14: =IF(F14=0,0,G14*$D$5) -> 0 | I14: =IF(F14=0,0,G14+H14) -> 0 | J14: =$F$4 -> 0.4 | K14: =IF(F14=0,0,I14*$J$4) -> 0 | L14: =IF(F14=0,0,I14*(1+$J$7)+K14) -> 0 | M14: =IF(F14=0,0,L14*(1+$D$4)) -> 0 | N14: =IF(F14=0,0,L14-I14) -> 0
A15: 9 | E15: 0 | F15: 0 | G15: =IF(F15=0,0,F15*$B$4*E15) -> 0 | H15: =IF(F15=0,0,G15*$D$5) -> 0 | I15: =IF(F15=0,0,G15+H15) -> 0 | J15: =$F$4 -> 0.4 | K15: =IF(F15=0,0,I15*$J$4) -> 0 | L15: =IF(F15=0,0,I15*(1+$J$7)+K15) -> 0 | M15: =IF(F15=0,0,L15*(1+$D$4)) -> 0 | N15: =IF(F15=0,0,L15-I15) -> 0
A16: 10 | E16: 0 | F16: 0 | G16: =IF(F16=0,0,F16*$B$4*E16) -> 0 | H16: =IF(F16=0,0,G16*$D$5) -> 0 | I16: =IF(F16=0,0,G16+H16) -> 0 | J16: =$F$4 -> 0.4 | K16: =IF(F16=0,0,I16*$J$4) -> 0 | L16: =IF(F16=0,0,I16*(1+$J$7)+K16) -> 0 | M16: =IF(F16=0,0,L16*(1+$D$4)) -> 0 | N16: =IF(F16=0,0,L16-I16) -> 0
A17: 11 | E17: 0 | F17: 0 | G17: =IF(F17=0,0,F17*$B$4*E17) -> 0 | H17: =IF(F17=0,0,G17*$D$5) -> 0 | I17: =IF(F17=0,0,G17+H17) -> 0 | J17: =$F$4 -> 0.4 | K17: =IF(F17=0,0,I17*$J$4) -> 0 | L17: =IF(F17=0,0,I17*(1+$J$7)+K17) -> 0 | M17: =IF(F17=0,0,L17*(1+$D$4)) -> 0 | N17: =IF(F17=0,0,L17-I17) -> 0
A18: 12 | E18: 0 | F18: 0 | G18: =IF(F18=0,0,F18*$B$4*E18) -> 0 | H18: =IF(F18=0,0,G18*$D$5) -> 0 | I18: =IF(F18=0,0,G18+H18) -> 0 | J18: =$F$4 -> 0.4 | K18: =IF(F18=0,0,I18*$J$4) -> 0 | L18: =IF(F18=0,0,I18*(1+$J$7)+K18) -> 0 | M18: =IF(F18=0,0,L18*(1+$D$4)) -> 0 | N18: =IF(F18=0,0,L18-I18) -> 0
A19: 13 | E19: 0 | F19: 0 | G19: =IF(F19=0,0,F19*$B$4*E19) -> 0 | H19: =IF(F19=0,0,G19*$D$5) -> 0 | I19: =IF(F19=0,0,G19+H19) -> 0 | J19: =$F$4 -> 0.4 | K19: =IF(F19=0,0,I19*$J$4) -> 0 | L19: =IF(F19=0,0,I19*(1+$J$7)+K19) -> 0 | M19: =IF(F19=0,0,L19*(1+$D$4)) -> 0 | N19: =IF(F19=0,0,L19-I19) -> 0
A20: 14 | E20: 0 | F20: 0 | G20: =IF(F20=0,0,F20*$B$4*E20) -> 0 | H20: =IF(F20=0,0,G20*$D$5) -> 0 | I20: =IF(F20=0,0,G20+H20) -> 0 | J20: =$F$4 -> 0.4 | K20: =IF(F20=0,0,I20*$J$4) -> 0 | L20: =IF(F20=0,0,I20*(1+$J$7)+K20) -> 0 | M20: =IF(F20=0,0,L20*(1+$D$4)) -> 0 | N20: =IF(F20=0,0,L20-I20) -> 0
... A35: 29 | E35: 0 | F35: 0 | G35: =IF(F35=0,0,F35*$B$4*E35) -> 0 | H35: =IF(F35=0,0,G35*$D$5) -> 0 | I35: =IF(F35=0,0,G35+H35) -> 0 | J35: =$F$4 -> 0.4 | K35: =IF(F35=0,0,I35*$J$4) -> 0 | L35: =IF(F35=0,0,I35*(1+$J$7)+K35) -> 0 | M35: =IF(F35=0,0,L35*(1+$D$4)) -> 0 | N35: =IF(F35=0,0,L35-I35) -> 0
A36: 30 | B36: COSTO DE ENVIO | C36: ENCOMIENDA | D36: Activo | E36: 1 | F36: 60 | G36: =IF(F36=0,0,F36*$B$4*E36) -> 93000 | H36: 0 | I36: =IF(F36=0,0,G36+H36) -> 93000 | J36: =$F$4 -> 0.4 | K36: 0 | L36: =IF(F36=0,0,I36*(1+$J$7)+K36) -> 130200 | M36: =IF(F36=0,0,L36*(1+$D$4)) -> 157542 | N36: =IF(F36=0,0,L36-I36) -> 37200
B37: ▶ TOTALES DEL PROYECTO | F37: =SUM(F7:F36) -> 10062 | G37: =SUM(G7:G36) -> 15903000 | H37: =SUM(H7:H36) -> 1581000 | I37: =SUM(I7:I36) -> 17484000 | J37: =F4 -> 0.4 | K37: =SUM(K7:K36) -> 869550 | L37: =SUM(L7:L36) -> 25347150 | M37: =SUM(M7:M36) -> 30670052 | N37: =SUM(N7:N36) -> 7863150
G42: COSTOS ADICIONALES DEL PROYECTO
G43: MANO DE OBRA
G44: CANT. TÉCNICOS | H44: DÍAS HÁBILES | I44: CANT. HORAS (×8 hs/día) | J44: VALOR HORA USD | K44: TOTAL USD | L44: DÓLAR + IVA | M44: TOTAL PESOS | N44: PESOS + IVA
G45: 0 | H45: 0 | I45: =IF(G45*H45=0,0,G45*H45*8) -> 0 | J45: 15.125 | K45: =IF(I45*J45=0,0,I45*J45) -> 0 | L45: =IF(K45=0,0,K45*(1+$D$4)) -> 0 | M45: =IF(K45=0,0,K45*$B$4) -> 0 | N45: =IF(M45=0,0,M45*(1+$D$4)) -> 0
G46: 0 | H46: 0 | I46: =IF(G46*H46=0,0,G46*H46*8) -> 0 | J46: 15.125 | K46: =IF(I46*J46=0,0,I46*J46) -> 0 | L46: =IF(K46=0,0,K46*(1+$D$4)) -> 0 | M46: =IF(K46=0,0,K46*$B$4) -> 0 | N46: =IF(M46=0,0,M46*(1+$D$4)) -> 0
G47: 0 | H47: 0 | I47: =IF(G47*H47=0,0,G47*H47*8) -> 0 | J47: 15.125 | K47: =IF(I47*J47=0,0,I47*J47) -> 0 | L47: =IF(K47=0,0,K47*(1+$D$4)) -> 0 | M47: =IF(K47=0,0,K47*$B$4) -> 0 | N47: =IF(M47=0,0,M47*(1+$D$4)) -> 0
G48: TOTAL MANO DE OBRA | K48: =SUM(K45:K47) -> 0 | L48: =SUM(L45:L47) -> 0 | M48: =SUM(M45:M47) -> 0 | N48: =SUM(N45:N47) -> 0
G50: KILÓMETROS / TRASLADOS
G51: KMS (ida) | H51: KMS (regreso) | I51: CANT. KMS (kms × 2) | J51: VALOR KM USD | K51: TOTAL USD | L51: DÓLAR + IVA | M51: TOTAL PESOS | N51: PESOS + IVA
G52: 0 | H52: =G52 -> 0 | I52: =IF(G52*2=0,0,G52*2) -> 0 | J52: 1.331 | K52: =IF(I52*J52=0,0,I52*J52) -> 0 | L52: =IF(K52=0,0,K52*$B$4*(1+$D$4)) -> 0 | M52: =IF(K52=0,0,K52*$B$4) -> 0 | N52: =IF(M52=0,0,M52*(1+$D$4)) -> 0
G53: 0 | H53: =G53 -> 0 | I53: =IF(G53*2=0,0,G53*2) -> 0 | J53: 1.331 | K53: =IF(I53*J53=0,0,I53*J53) -> 0 | L53: =IF(K53=0,0,K53*$B$4*(1+$D$4)) -> 0 | M53: =IF(K53=0,0,K53*$B$4) -> 0 | N53: =IF(M53=0,0,M53*(1+$D$4)) -> 0
G54: 0 | H54: =G54 -> 0 | I54: =IF(G54*2=0,0,G54*2) -> 0 | J54: 1.331 | K54: =IF(I54*J54=0,0,I54*J54) -> 0 | L54: =IF(K54=0,0,K54*$B$4*(1+$D$4)) -> 0 | M54: =IF(K54=0,0,K54*$B$4) -> 0 | N54: =IF(M54=0,0,M54*(1+$D$4)) -> 0
G55: TOTAL KILÓMETROS | K55: =SUM(K52:K54) -> 0 | L55: =SUM(L52:L54) -> 0 | M55: =SUM(M52:M54) -> 0 | N55: =SUM(N52:N54) -> 0
A59: COSTO PROYECTO FINAL
A60: PROYECTO
A61: N° | B61: DESCRIPCION | C61: P. VENTA SIN IVA | D61: P. VENTA CON IVA
A62: 1 | B62: PRODUCTOS / SERVICIO | C62: =L37 -> 25347150 | D62: =M37 -> 30670052
A63: 2 | B63: MANO DE OBRA | C63: =M48 -> 0 | D63: =N48 -> 0
A64: 3 | B64: KILÓMETROS / TRASLADOS | C64: =M55 -> 0 | D64: =N55 -> 0
A65: TOTAL | C65: =SUM(C62:C64) -> 25347150 | D65: =SUM(D62:D64) -> 30670052

Sheet Proyectos de Venta (ORIGINAL)
A1: GESTIÓN DE PROYECTOS DE VENTA · Argentina
A2: Actualizado: 21/05/2026 | 🔵 Inputs en azul | ⚫ Fórmulas en negro | 🟢 Resultados clave | MK variable — recomendado 46%
A3: ⚙ PARÁMETROS — Argentina 2025
A4: DÓLAR | B4: 1550 | C4: IVA (%) | D4: 0.21 | E4: MK (%) | F4: 0.45 | G4: MK MÍNIMO (%) | H4: 0.3 | I4: • El 46% es el recomendado por la empresa • Cada fila acepta un MK distinto • El semáforo alerta si estás por debajo del mínimo
A5: INFLACIÓN ANUAL | B5: 0.3 | C5: IMPREVISTOS (%) | D5: 0 | E5: CUOTA (Meses) | F5: 12 | G5: CANT. AÑOS PROY. | H5: 0
A6: N° | B6: PRODUCTO / SERVICIO | C6: PROVEEDOR | D6: ESTADO | E6: CANT. | F6: COSTO USD | G6: COSTO ARS | H6: IMPREVISTOS | I6: COSTO REAL SIN IVA | J6: COSTO REAL CON IVA | K6: MK (%) | L6: P. VENTA SIN IVA | M6: P. VENTA CON IVA | N6: UTILIDAD ARS
A7: 1 | B7: PRUEBAS | E7: 1 | F7: 10000 | G7: =IF(F7=0,0,F7*$B$4*E7) -> 15500000 | H7: =IF(F7=0,0,G7*$D$5) -> 0 | I7: =IF(F7=0,0,G7+H7) -> 15500000 | J7: =IF(F7=0,0,I7*(1+$D$4)) -> 18755000 | K7: 0.46 | L7: =IF(F7=0,0,I7*(1+$F$4)) -> 22475000 | M7: =IF(F7=0,0,L7*(1+$D$4)) -> 27194750 | N7: =IF(F7=0,0,L7-I7) -> 6975000
A8: 2 | B8: PRUEBA 2 | E8: 100 | F8: 2 | G8: =IF(F8=0,0,F8*$B$4*E8) -> 310000 | H8: =IF(F8=0,0,G8*$D$5) -> 0 | I8: =IF(F8=0,0,G8+H8) -> 310000 | J8: =IF(F8=0,0,I8*(1+$D$4)) -> 375100 | K8: 0.46 | L8: =IF(F8=0,0,I8*(1+$F$4)) -> 449500 | M8: =IF(F8=0,0,L8*(1+$D$4)) -> 543895 | N8: =IF(F8=0,0,L8-I8) -> 139500
A9: 3 | E9: 0 | F9: 0 | G9: =IF(F9=0,0,F9*$B$4*E9) -> 0 | H9: =IF(F9=0,0,G9*$D$5) -> 0 | I9: =IF(F9=0,0,G9+H9) -> 0 | J9: =IF(F9=0,0,I9*(1+$D$4)) -> 0 | K9: 0.46 | L9: =IF(F9=0,0,I9*(1+$F$4)) -> 0 | M9: =IF(F9=0,0,L9*(1+$D$4)) -> 0 | N9: =IF(F9=0,0,L9-I9) -> 0
A10: 4 | E10: 0 | F10: 0 | G10: =IF(F10=0,0,F10*$B$4*E10) -> 0 | H10: =IF(F10=0,0,G10*$D$5) -> 0 | I10: =IF(F10=0,0,G10+H10) -> 0 | J10: =IF(F10=0,0,I10*(1+$D$4)) -> 0 | K10: 0.46 | L10: =IF(F10=0,0,I10*(1+$F$4)) -> 0 | M10: =IF(F10=0,0,L10*(1+$D$4)) -> 0 | N10: =IF(F10=0,0,L10-I10) -> 0
A11: 5 | E11: 0 | F11: 0 | G11: =IF(F11=0,0,F11*$B$4*E11) -> 0 | H11: =IF(F11=0,0,G11*$D$5) -> 0 | I11: =IF(F11=0,0,G11+H11) -> 0 | J11: =IF(F11=0,0,I11*(1+$D$4)) -> 0 | K11: 0.46 | L11: =IF(F11=0,0,I11*(1+$F$4)) -> 0 | M11: =IF(F11=0,0,L11*(1+$D$4)) -> 0 | N11: =IF(F11=0,0,L11-I11) -> 0
A12: 6 | E12: 0 | F12: 0 | G12: =IF(F12=0,0,F12*$B$4*E12) -> 0 | H12: =IF(F12=0,0,G12*$D$5) -> 0 | I12: =IF(F12=0,0,G12+H12) -> 0 | J12: =IF(F12=0,0,I12*(1+$D$4)) -> 0 | K12: 0.46 | L12: =IF(F12=0,0,I12*(1+$F$4)) -> 0 | M12: =IF(F12=0,0,L12*(1+$D$4)) -> 0 | N12: =IF(F12=0,0,L12-I12) -> 0
A13: 7 | E13: 0 | F13: 0 | G13: =IF(F13=0,0,F13*$B$4*E13) -> 0 | H13: =IF(F13=0,0,G13*$D$5) -> 0 | I13: =IF(F13=0,0,G13+H13) -> 0 | J13: =IF(F13=0,0,I13*(1+$D$4)) -> 0 | K13: 0.46 | L13: =IF(F13=0,0,I13*(1+$F$4)) -> 0 | M13: =IF(F13=0,0,L13*(1+$D$4)) -> 0 | N13: =IF(F13=0,0,L13-I13) -> 0
A14: 8 | E14: 0 | F14: 0 | G14: =IF(F14=0,0,F14*$B$4*E14) -> 0 | H14: =IF(F14=0,0,G14*$D$5) -> 0 | I14: =IF(F14=0,0,G14+H14) -> 0 | J14: =IF(F14=0,0,I14*(1+$D$4)) -> 0 | K14: 0.46 | L14: =IF(F14=0,0,I14*(1+$F$4)) -> 0 | M14: =IF(F14=0,0,L14*(1+$D$4)) -> 0 | N14: =IF(F14=0,0,L14-I14) -> 0
A15: 9 | E15: 0 | F15: 0 | G15: =IF(F15=0,0,F15*$B$4*E15) -> 0 | H15: =IF(F15=0,0,G15*$D$5) -> 0 | I15: =IF(F15=0,0,G15+H15) -> 0 | J15: =IF(F15=0,0,I15*(1+$D$4)) -> 0 | K15: 0.46 | L15: =IF(F15=0,0,I15*(1+$F$4)) -> 0 | M15: =IF(F15=0,0,L15*(1+$D$4)) -> 0 | N15: =IF(F15=0,0,L15-I15) -> 0
A16: 10 | E16: 0 | F16: 0 | G16: =IF(F16=0,0,F16*$B$4*E16) -> 0 | H16: =IF(F16=0,0,G16*$D$5) -> 0 | I16: =IF(F16=0,0,G16+H16) -> 0 | J16: =IF(F16=0,0,I16*(1+$D$4)) -> 0 | K16: 0.46 | L16: =IF(F16=0,0,I16*(1+$F$4)) -> 0 | M16: =IF(F16=0,0,L16*(1+$D$4)) -> 0 | N16: =IF(F16=0,0,L16-I16) -> 0
A17: 11 | E17: 0 | F17: 0 | G17: =IF(F17=0,0,F17*$B$4*E17) -> 0 | H17: =IF(F17=0,0,G17*$D$5) -> 0 | I17: =IF(F17=0,0,G17+H17) -> 0 | J17: =IF(F17=0,0,I17*(1+$D$4)) -> 0 | K17: 0.46 | L17: =IF(F17=0,0,I17*(1+$F$4)) -> 0 | M17: =IF(F17=0,0,L17*(1+$D$4)) -> 0 | N17: =IF(F17=0,0,L17-I17) -> 0
A18: 12 | E18: 0 | F18: 0 | G18: =IF(F18=0,0,F18*$B$4*E18) -> 0 | H18: =IF(F18=0,0,G18*$D$5) -> 0 | I18: =IF(F18=0,0,G18+H18) -> 0 | J18: =IF(F18=0,0,I18*(1+$D$4)) -> 0 | K18: 0.46 | L18: =IF(F18=0,0,I18*(1+$F$4)) -> 0 | M18: =IF(F18=0,0,L18*(1+$D$4)) -> 0 | N18: =IF(F18=0,0,L18-I18) -> 0
A19: 13 | E19: 0 | F19: 0 | G19: =IF(F19=0,0,F19*$B$4*E19) -> 0 | H19: =IF(F19=0,0,G19*$D$5) -> 0 | I19: =IF(F19=0,0,G19+H19) -> 0 | J19: =IF(F19=0,0,I19*(1+$D$4)) -> 0 | K19: 0.46 | L19: =IF(F19=0,0,I19*(1+$F$4)) -> 0 | M19: =IF(F19=0,0,L19*(1+$D$4)) -> 0 | N19: =IF(F19=0,0,L19-I19) -> 0
A20: 14 | E20: 0 | F20: 0 | G20: =IF(F20=0,0,F20*$B$4*E20) -> 0 | H20: =IF(F20=0,0,G20*$D$5) -> 0 | I20: =IF(F20=0,0,G20+H20) -> 0 | J20: =IF(F20=0,0,I20*(1+$D$4)) -> 0 | K20: 0.46 | L20: =IF(F20=0,0,I20*(1+$F$4)) -> 0 | M20: =IF(F20=0,0,L20*(1+$D$4)) -> 0 | N20: =IF(F20=0,0,L20-I20) -> 0
... A35: 29 | E35: 0 | F35: 0 | G35: =IF(F35=0,0,F35*$B$4*E35) -> 0 | H35: =IF(F35=0,0,G35*$D$5) -> 0 | I35: =IF(F35=0,0,G35+H35) -> 0 | J35: =IF(F35=0,0,I35*(1+$D$4)) -> 0 | K35: 0.46 | L35: =IF(F35=0,0,I35*(1+$F$4)) -> 0 | M35: =IF(F35=0,0,L35*(1+$D$4)) -> 0 | N35: =IF(F35=0,0,L35-I35) -> 0
A36: 30 | B36: COSTO DE ENVIO | C36: ENCOMIENDA | D36: Activo | E36: 0 | F36: 0 | G36: =IF(F36=0,0,F36*$B$4*E36) -> 0 | H36: =IF(F36=0,0,G36*$D$5) -> 0 | I36: =IF(F36=0,0,G36+H36) -> 0 | J36: =IF(F36=0,0,I36*(1+$D$4)) -> 0 | K36: 0.46 | L36: =IF(F36=0,0,I36*(1+$F$4)) -> 0 | M36: =IF(F36=0,0,L36*(1+$D$4)) -> 0 | N36: =IF(F36=0,0,L36-I36) -> 0
B37: ▶ TOTALES DEL PROYECTO | F37: =SUM(F7:F36) -> 10002 | G37: =SUM(G7:G36) -> 15810000 | H37: =SUM(H7:H36) -> 0 | I37: =SUM(I7:I36) -> 15810000 | J37: =SUM(J7:J36) -> 19130100 | K37: =F4 -> 0.45 | L37: =SUM(L7:L36) -> 22924500 | M37: =SUM(M7:M36) -> 27738645 | N37: =SUM(N7:N36) -> 7114500
G42: COSTOS ADICIONALES DEL PROYECTO
G43: MANO DE OBRA
G44: CANT. TÉCNICOS | H44: DÍAS HÁBILES | I44: CANT. HORAS (×8 hs/día) | J44: VALOR HORA USD | K44: TOTAL USD | L44: DÓLAR + IVA | M44: TOTAL PESOS | N44: PESOS + IVA
G45: 0 | H45: 0 | I45: =IF(G45*H45=0,0,G45*H45*8) -> 0 | J45: 15.125 | K45: =IF(I45*J45=0,0,I45*J45) -> 0 | L45: =IF(K45=0,0,K45*(1+$D$4)) -> 0 | M45: =IF(K45=0,0,K45*$B$4) -> 0 | N45: =IF(M45=0,0,M45*(1+$D$4)) -> 0
G46: 0 | H46: 0 | I46: =IF(G46*H46=0,0,G46*H46*8) -> 0 | J46: 15.125 | K46: =IF(I46*J46=0,0,I46*J46) -> 0 | L46: =IF(K46=0,0,K46*(1+$D$4)) -> 0 | M46: =IF(K46=0,0,K46*$B$4) -> 0 | N46: =IF(M46=0,0,M46*(1+$D$4)) -> 0
G47: 0 | H47: 0 | I47: =IF(G47*H47=0,0,G47*H47*8) -> 0 | J47: 15.125 | K47: =IF(I47*J47=0,0,I47*J47) -> 0 | L47: =IF(K47=0,0,K47*(1+$D$4)) -> 0 | M47: =IF(K47=0,0,K47*$B$4) -> 0 | N47: =IF(M47=0,0,M47*(1+$D$4)) -> 0
G48: TOTAL MANO DE OBRA | K48: =SUM(K45:K47) -> 0 | L48: =SUM(L45:L47) -> 0 | M48: =SUM(M45:M47) -> 0 | N48: =SUM(N45:N47) -> 0
G50: KILÓMETROS / TRASLADOS
G51: KMS (ida) | H51: KMS (regreso) | I51: CANT. KMS (kms × 2) | J51: VALOR KM USD | K51: TOTAL USD | L51: DÓLAR + IVA | M51: TOTAL PESOS | N51: PESOS + IVA
G52: 0 | H52: =G52 -> 0 | I52: =IF(G52*2=0,0,G52*2) -> 0 | J52: 1.331 | K52: =IF(I52*J52=0,0,I52*J52) -> 0 | L52: =IF(K52=0,0,K52*$B$4*(1+$D$4)) -> 0 | M52: =IF(K52=0,0,K52*$B$4) -> 0 | N52: =IF(M52=0,0,M52*(1+$D$4)) -> 0
G53: 0 | H53: =G53 -> 0 | I53: =IF(G53*2=0,0,G53*2) -> 0 | J53: 1.331 | K53: =IF(I53*J53=0,0,I53*J53) -> 0 | L53: =IF(K53=0,0,K53*$B$4*(1+$D$4)) -> 0 | M53: =IF(K53=0,0,K53*$B$4) -> 0 | N53: =IF(M53=0,0,M53*(1+$D$4)) -> 0
G54: 0 | H54: =G54 -> 0 | I54: =IF(G54*2=0,0,G54*2) -> 0 | J54: 1.331 | K54: =IF(I54*J54=0,0,I54*J54) -> 0 | L54: =IF(K54=0,0,K54*$B$4*(1+$D$4)) -> 0 | M54: =IF(K54=0,0,K54*$B$4) -> 0 | N54: =IF(M54=0,0,M54*(1+$D$4)) -> 0
G55: TOTAL KILÓMETROS | K55: =SUM(K52:K54) -> 0 | L55: =SUM(L52:L54) -> 0 | M55: =SUM(M52:M54) -> 0 | N55: =SUM(N52:N54) -> 0
A59: COSTO PROYECTO FINAL
A60: PROYECTO
A61: N° | B61: DESCRIPCION | C61: COSTO REAL SIN IVA | D61: COSTO REAL CON IVA | E61: P. VENTA SIN IVA | F61: P. VENTA CON IVA
A62: 1 | B62: PRODUCTOS / SERVICIO | C62: =I37 -> 15810000 | D62: =J37 -> 19130100 | E62: =L37 -> 22924500 | F62: =M37 -> 27738645
A63: 2 | B63: MANO DE OBRA | C63: =K48 -> 0 | D63: =L48 -> 0 | E63: =M48 -> 0 | F63: =N48 -> 0
A64: 3 | B64: KILÓMETROS / TRASLADOS | C64: =K55 -> 0 | D64: =L55 -> 0 | E64: =M55 -> 0 | F64: =N55 -> 0
A65: TOTAL | E65: =SUM(E62:E64) -> 22924500 | F65: =SUM(F62:F64) -> 27738645

Sheet Proyectos de Venta
A1: GESTIÓN DE PROYECTOS DE VENTA · Argentina
A2: Actualizado: 21/05/2026 | 🔵 Inputs en azul | ⚫ Fórmulas en negro | 🟢 Resultados clave | MK variable — recomendado 46%
A3: ⚙ PARÁMETROS — Argentina 2025
A4: DÓLAR | B4: 1550 | C4: IVA (%) | D4: 0.21 | E4: MK (%) | F4: 0.46 | G4: MK MÍNIMO (%) | H4: 0.3 | I4: COMISIÓN (%) | J4: 0.05
A5: INFLACIÓN ANUAL | B5: 0.3 | C5: IMPREVISTOS (%) | D5: 0.1 | E5: CUOTA VARIABLE (Meses) | F5: 12 | G5: CANT. AÑOS PROY. | H5: 0 | I5: COMODATO %
A6: N° | B6: PRODUCTO / SERVICIO | C6: PROVEEDOR | D6: ESTADO | E6: CANT. | F6: COSTO USD | G6: COSTO ARS | H6: IMPREVISTOS | I6: COSTO REAL SIN IVA | J6: MK (%) | K6: COMISIÓN | L6: P. VENTA SIN IVA | M6: P. VENTA CON IVA | N6: UTILIDAD ARS
A7: SISTEMA DE ALARMA | E7: 0 | F7: 0 | G7: =IF(F7=0,0,F7*$B$4*E7) -> 0 | H7: =IF(F7=0,0,G7*$D$5) -> 0 | I7: =IF(F7=0,0,G7+H7) -> 0 | J7: =$F$4 -> 0.46 | K7: =IF(F7=0,0,I7*$J$4) -> 0 | L7: =IF(F7=0,0,I7*(1+$J$7)+K7) -> 0 | M7: =IF(F7=0,0,L7*(1+$D$4)) -> 0 | N7: =IF(F7=0,0,L7-I7) -> 0
A8: 2 | B8: Central de Alarma DSC PowerSeries NEO (HS2016/HS2032/HS2064/HS2128 o similar, según cantidad de zonas + 25% holgura) | E8: 0 | F8: 0 | G8: =IF(F8=0,0,F8*$B$4*E8) -> 0 | H8: =IF(F8=0,0,G8*$D$5) -> 0 | I8: =IF(F8=0,0,G8+H8) -> 0 | J8: =$F$4 -> 0.46 | K8: =IF(F8=0,0,I8*$J$4) -> 0 | L8: =IF(F8=0,0,I8*(1+$J$7)+K8) -> 0 | M8: =IF(F8=0,0,L8*(1+$D$4)) -> 0 | N8: =IF(F8=0,0,L8-I8) -> 0
A9: 3 | B9: Gabinete metálico para Panel de Alarma | E9: 0 | F9: 0 | G9: =IF(F9=0,0,F9*$B$4*E9) -> 0 | H9: =IF(F9=0,0,G9*$D$5) -> 0 | I9: =IF(F9=0,0,G9+H9) -> 0 | J9: =$F$4 -> 0.46 | K9: =IF(F9=0,0,I9*$J$4) -> 0 | L9: =IF(F9=0,0,I9*(1+$J$7)+K9) -> 0 | M9: =IF(F9=0,0,L9*(1+$D$4)) -> 0 | N9: =IF(F9=0,0,L9-I9) -> 0
A10: 4 | B10: Gabinete para fuente de alimentación de sirenas | E10: 0 | F10: 0 | G10: =IF(F10=0,0,F10*$B$4*E10) -> 0 | H10: =IF(F10=0,0,G10*$D$5) -> 0 | I10: =IF(F10=0,0,G10+H10) -> 0 | J10: =$F$4 -> 0.46 | K10: =IF(F10=0,0,I10*$J$4) -> 0 | L10: =IF(F10=0,0,I10*(1+$J$7)+K10) -> 0 | M10: =IF(F10=0,0,L10*(1+$D$4)) -> 0 | N10: =IF(F10=0,0,L10-I10) -> 0
A11: 5 | B11: Módulo de Salida de Alta Corriente DSC HSM2204 | E11: 0 | F11: 0 | G11: =IF(F11=0,0,F11*$B$4*E11) -> 0 | H11: =IF(F11=0,0,G11*$D$5) -> 0 | I11: =IF(F11=0,0,G11+H11) -> 0 | J11: =$F$4 -> 0.46 | K11: =IF(F11=0,0,I11*$J$4) -> 0 | L11: =IF(F11=0,0,I11*(1+$J$7)+K11) -> 0 | M11: =IF(F11=0,0,L11*(1+$D$4)) -> 0 | N11: =IF(F11=0,0,L11-I11) -> 0
A12: 6 | B12: Placa Expansora de Zonas Cableadas DSC HSM2108 | E12: 0 | F12: 0 | G12: =IF(F12=0,0,F12*$B$4*E12) -> 0 | H12: =IF(F12=0,0,G12*$D$5) -> 0 | I12: =IF(F12=0,0,G12+H12) -> 0 | J12: =$F$4 -> 0.46 | K12: =IF(F12=0,0,I12*$J$4) -> 0 | L12: =IF(F12=0,0,I12*(1+$J$7)+K12) -> 0 | M12: =IF(F12=0,0,L12*(1+$D$4)) -> 0 | N12: =IF(F12=0,0,L12-I12) -> 0
A13: 7 | B13: Fuente de alimentación auxiliar supervisada + juego de relay | E13: 0 | F13: 0 | G13: =IF(F13=0,0,F13*$B$4*E13) -> 0 | H13: =IF(F13=0,0,G13*$D$5) -> 0 | I13: =IF(F13=0,0,G13+H13) -> 0 | J13: =$F$4 -> 0.46 | K13: =IF(F13=0,0,I13*$J$4) -> 0 | L13: =IF(F13=0,0,I13*(1+$J$7)+K13) -> 0 | M13: =IF(F13=0,0,L13*(1+$D$4)) -> 0 | N13: =IF(F13=0,0,L13-I13) -> 0
A14: 8 | B14: Sensor de Movimiento PIR doble tecnología, anti-mascota (38kg), 15m/90° | E14: 0 | F14: 0 | G14: =IF(F14=0,0,F14*$B$4*E14) -> 0 | H14: =IF(F14=0,0,G14*$D$5) -> 0 | I14: =IF(F14=0,0,G14+H14) -> 0 | J14: =$F$4 -> 0.46 | K14: =IF(F14=0,0,I14*$J$4) -> 0 | L14: =IF(F14=0,0,I14*(1+$J$7)+K14) -> 0 | M14: =IF(F14=0,0,L14*(1+$D$4)) -> 0 | N14: =IF(F14=0,0,L14-I14) -> 0
A15: 9 | B15: Detector inalámbrico de Rotura de Vidrios (360°, 7,6m) | E15: 0 | F15: 0 | G15: =IF(F15=0,0,F15*$B$4*E15) -> 0 | H15: =IF(F15=0,0,G15*$D$5) -> 0 | I15: =IF(F15=0,0,G15+H15) -> 0 | J15: =$F$4 -> 0.46 | K15: =IF(F15=0,0,I15*$J$4) -> 0 | L15: =IF(F15=0,0,I15*(1+$J$7)+K15) -> 0 | M15: =IF(F15=0,0,L15*(1+$D$4)) -> 0 | N15: =IF(F15=0,0,L15-I15) -> 0
A16: 10 | B16: Contactos Magnéticos inalámbricos de apertura de puertas | E16: 0 | F16: 0 | G16: =IF(F16=0,0,F16*$B$4*E16) -> 0 | H16: =IF(F16=0,0,G16*$D$5) -> 0 | I16: =IF(F16=0,0,G16+H16) -> 0 | J16: =$F$4 -> 0.46 | K16: =IF(F16=0,0,I16*$J$4) -> 0 | L16: =IF(F16=0,0,I16*(1+$J$7)+K16) -> 0 | M16: =IF(F16=0,0,L16*(1+$D$4)) -> 0 | N16: =IF(F16=0,0,L16-I16) -> 0
A17: 11 | B17: Llaveros inalámbricos de apertura/cierre/pánico | E17: 0 | F17: 0 | G17: =IF(F17=0,0,F17*$B$4*E17) -> 0 | H17: =IF(F17=0,0,G17*$D$5) -> 0 | I17: =IF(F17=0,0,G17+H17) -> 0 | J17: =$F$4 -> 0.46 | K17: =IF(F17=0,0,I17*$J$4) -> 0 | L17: =IF(F17=0,0,I17*(1+$J$7)+K17) -> 0 | M17: =IF(F17=0,0,L17*(1+$D$4)) -> 0 | N17: =IF(F17=0,0,L17-I17) -> 0
A18: SISTEMA DE INCENDIO | E18: 0 | F18: 0 | G18: =IF(F18=0,0,F18*$B$4*E18) -> 0 | H18: =IF(F18=0,0,G18*$D$5) -> 0 | I18: =IF(F18=0,0,G18+H18) -> 0 | J18: =$F$4 -> 0.46 | K18: =IF(F18=0,0,I18*$J$4) -> 0 | L18: =IF(F18=0,0,I18*(1+$J$7)+K18) -> 0 | M18: =IF(F18=0,0,L18*(1+$D$4)) -> 0 | N18: =IF(F18=0,0,L18-I18) -> 0
A19: 13 | B19: Sensores de Humo Fotoeléctrico, 2 hilos, 12/24 Vcc | E19: 0 | F19: 0 | G19: =IF(F19=0,0,F19*$B$4*E19) -> 0 | H19: =IF(F19=0,0,G19*$D$5) -> 0 | I19: =IF(F19=0,0,G19+H19) -> 0 | J19: =$F$4 -> 0.46 | K19: =IF(F19=0,0,I19*$J$4) -> 0 | L19: =IF(F19=0,0,I19*(1+$J$7)+K19) -> 0 | M19: =IF(F19=0,0,L19*(1+$D$4)) -> 0 | N19: =IF(F19=0,0,L19-I19) -> 0
A20: 14 | B20: Sensores Térmicos de Incendio, 2 hilos, 12/24 Vcc | E20: 0 | F20: 0 | G20: =IF(F20=0,0,F20*$B$4*E20) -> 0 | H20: =IF(F20=0,0,G20*$D$5) -> 0 | I20: =IF(F20=0,0,G20+H20) -> 0 | J20: =$F$4 -> 0.46 | K20: =IF(F20=0,0,I20*$J$4) -> 0 | L20: =IF(F20=0,0,I20*(1+$J$7)+K20) -> 0 | M20: =IF(F20=0,0,L20*(1+$D$4)) -> 0 | N20: =IF(F20=0,0,L20-I20) -> 0
A21: 15 | B21: Avisadores Manuales de Incendio (NBG 12LSP Notifier o similar) | E21: 0 | F21: 0 | G21: =IF(F21=0,0,F21*$B$4*E21) -> 0 | H21: =IF(F21=0,0,G21*$D$5) -> 0 | I21: =IF(F21=0,0,G21+H21) -> 0 | J21: =$F$4 -> 0.46 | K21: =IF(F21=0,0,I21*$J$4) -> 0 | L21: =IF(F21=0,0,I21*(1+$J$7)+K21) -> 0 | M21: =IF(F21=0,0,L21*(1+$D$4)) -> 0 | N21: =IF(F21=0,0,L21-I21) -> 0
A22: 16 | B22: Sirena de Aviso de Incendio con estrobo (110dB, selección de candelas) | E22: 0 | F22: 0 | G22: =IF(F22=0,0,F22*$B$4*E22) -> 0 | H22: =IF(F22=0,0,G22*$D$5) -> 0 | I22: =IF(F22=0,0,G22+H22) -> 0 | J22: =$F$4 -> 0.46 | K22: =IF(F22=0,0,I22*$J$4) -> 0 | L22: =IF(F22=0,0,I22*(1+$J$7)+K22) -> 0 | M22: =IF(F22=0,0,L22*(1+$D$4)) -> 0 | N22: =IF(F22=0,0,L22-I22) -> 0
A23: SIRENA | E23: 0 | F23: 0 | G23: =IF(F23=0,0,F23*$B$4*E23) -> 0 | H23: =IF(F23=0,0,G23*$D$5) -> 0 | I23: =IF(F23=0,0,G23+H23) -> 0 | J23: =$F$4 -> 0.46 | K23: =IF(F23=0,0,I23*$J$4) -> 0 | L23: =IF(F23=0,0,I23*(1+$J$7)+K23) -> 0 | M23: =IF(F23=0,0,L23*(1+$D$4)) -> 0 | N23: =IF(F23=0,0,L23-I23) -> 0
A24: 18 | B24: Sirena Piezoeléctrica interior (120dB) | E24: 0 | F24: 0 | G24: =IF(F24=0,0,F24*$B$4*E24) -> 0 | H24: =IF(F24=0,0,G24*$D$5) -> 0 | I24: =IF(F24=0,0,G24+H24) -> 0 | J24: =$F$4 -> 0.46 | K24: =IF(F24=0,0,I24*$J$4) -> 0 | L24: =IF(F24=0,0,I24*(1+$J$7)+K24) -> 0 | M24: =IF(F24=0,0,L24*(1+$D$4)) -> 0 | N24: =IF(F24=0,0,L24-I24) -> 0
A25: 19 | B25: Sirena Exterior Magneto dinámica con Flash (118dB, 30W+Flash) | E25: 0 | F25: 0 | G25: =IF(F25=0,0,F25*$B$4*E25) -> 0 | H25: =IF(F25=0,0,G25*$D$5) -> 0 | I25: =IF(F25=0,0,G25+H25) -> 0 | J25: =$F$4 -> 0.46 | K25: =IF(F25=0,0,I25*$J$4) -> 0 | L25: =IF(F25=0,0,I25*(1+$J$7)+K25) -> 0 | M25: =IF(F25=0,0,L25*(1+$D$4)) -> 0 | N25: =IF(F25=0,0,L25-I25) -> 0
A26: COMUNICACION | E26: 0 | F26: 0 | G26: =IF(F26=0,0,F26*$B$4*E26) -> 0 | H26: =IF(F26=0,0,G26*$D$5) -> 0 | I26: =IF(F26=0,0,G26+H26) -> 0 | J26: =$F$4 -> 0.46 | K26: =IF(F26=0,0,I26*$J$4) -> 0 | L26: =IF(F26=0,0,I26*(1+$J$7)+K26) -> 0 | M26: =IF(F26=0,0,L26*(1+$D$4)) -> 0 | N26: =IF(F26=0,0,L26-I26) -> 0
A27: 21 | B27: Comunicador de Alarma celular 3G/2G + Ethernet, compatible DSC PowerSeries NEO | E27: 0 | F27: 0 | G27: =IF(F27=0,0,F27*$B$4*E27) -> 0 | H27: =IF(F27=0,0,G27*$D$5) -> 0 | I27: =IF(F27=0,0,G27+H27) -> 0 | J27: =$F$4 -> 0.46 | K27: =IF(F27=0,0,I27*$J$4) -> 0 | L27: =IF(F27=0,0,I27*(1+$J$7)+K27) -> 0 | M27: =IF(F27=0,0,L27*(1+$D$4)) -> 0 | N27: =IF(F27=0,0,L27-I27) -> 0
A28: 22 | B28: Licencia/habilitación App Connect Alarm | E28: 0 | F28: 0 | G28: =IF(F28=0,0,F28*$B$4*E28) -> 0 | H28: =IF(F28=0,0,G28*$D$5) -> 0 | I28: =IF(F28=0,0,G28+H28) -> 0 | J28: =$F$4 -> 0.46 | K28: =IF(F28=0,0,I28*$J$4) -> 0 | L28: =IF(F28=0,0,I28*(1+$J$7)+K28) -> 0 | M28: =IF(F28=0,0,L28*(1+$D$4)) -> 0 | N28: =IF(F28=0,0,L28-I28) -> 0
A29: SISTEMA DE CCTV | E29: 0 | F29: 0 | G29: =IF(F29=0,0,F29*$B$4*E29) -> 0 | H29: =IF(F29=0,0,G29*$D$5) -> 0 | I29: =IF(F29=0,0,G29+H29) -> 0 | J29: =$F$4 -> 0.46 | K29: =IF(F29=0,0,I29*$J$4) -> 0 | L29: =IF(F29=0,0,I29*(1+$J$7)+K29) -> 0 | M29: =IF(F29=0,0,L29*(1+$D$4)) -> 0 | N29: =IF(F29=0,0,L29-I29) -> 0
A30: 24 | B30: NVR Hikvision DS-7608NI-K2/8P (o DS-7616NI-K2/16P / DS-7632NI-K2/16P | E30: 0 | F30: 0 | G30: =IF(F30=0,0,F30*$B$4*E30) -> 0 | H30: =IF(F30=0,0,G30*$D$5) -> 0 | I30: =IF(F30=0,0,G30+H30) -> 0 | J30: =$F$4 -> 0.46 | K30: =IF(F30=0,0,I30*$J$4) -> 0 | L30: =IF(F30=0,0,I30*(1+$J$7)+K30) -> 0 | M30: =IF(F30=0,0,L30*(1+$D$4)) -> 0 | N30: =IF(F30=0,0,L30-I30) -> 0
A31: 25 | B31: Discos rígidos SATA para NVR (uso 24/7, hasta 6TB c/u) | E31: 0 | F31: 0 | G31: =IF(F31=0,0,F31*$B$4*E31) -> 0 | H31: =IF(F31=0,0,G31*$D$5) -> 0 | I31: =IF(F31=0,0,G31+H31) -> 0 | J31: =$F$4 -> 0.46 | K31: =IF(F31=0,0,I31*$J$4) -> 0 | L31: =IF(F31=0,0,I31*(1+$J$7)+K31) -> 0 | M31: =IF(F31=0,0,L31*(1+$D$4)) -> 0 | N31: =IF(F31=0,0,L31-I31) -> 0
A32: 26 | B32: Bandeja perforada para rack | E32: 0 | F32: 0 | G32: =IF(F32=0,0,F32*$B$4*E32) -> 0 | H32: =IF(F32=0,0,G32*$D$5) -> 0 | I32: =IF(F32=0,0,G32+H32) -> 0 | J32: =$F$4 -> 0.46 | K32: =IF(F32=0,0,I32*$J$4) -> 0 | L32: =IF(F32=0,0,I32*(1+$J$7)+K32) -> 0 | M32: =IF(F32=0,0,L32*(1+$D$4)) -> 0 | N32: =IF(F32=0,0,L32-I32) -> 0
A33: 27 | B33: Cámaras IP Domo interior HIKVISION DS-2CD1343G0-I | E33: 0 | F33: 0 | G33: =IF(F33=0,0,F33*$B$4*E33) -> 0 | H33: =IF(F33=0,0,G33*$D$5) -> 0 | I33: =IF(F33=0,0,G33+H33) -> 0 | J33: =$F$4 -> 0.46 | K33: =IF(F33=0,0,I33*$J$4) -> 0 | L33: =IF(F33=0,0,I33*(1+$J$7)+K33) -> 0 | M33: =IF(F33=0,0,L33*(1+$D$4)) -> 0 | N33: =IF(F33=0,0,L33-I33) -> 0
A34: 28 | B34: Cámaras IP Bullet exterior HIKVISION DS-2CD1043G2-LIUF(2.8mm) | E34: 0 | F34: 0 | G34: =IF(F34=0,0,F34*$B$4*E34) -> 0 | H34: =IF(F34=0,0,G34*$D$5) -> 0 | I34: =IF(F34=0,0,G34+H34) -> 0 | J34: =$F$4 -> 0.46 | K34: =IF(F34=0,0,I34*$J$4) -> 0 | L34: =IF(F34=0,0,I34*(1+$J$7)+K34) -> 0 | M34: =IF(F34=0,0,L34*(1+$D$4)) -> 0 | N34: =IF(F34=0,0,L34-I34) -> 0
A35: 29 | B35: Switch PoE adicional (si se excede la capacidad PoE nativa del NVR)
A36: 30 | B36: Cable UTP Cat6 (interior/exterior según tramo)
A37: 31 | B37: Conectores RJ45 y accesorios de terminación
A38: ALIMENTACION Y TABLEROS
B39: Tablero metálico dedicado a Intrusión/Incendio (con disyuntor, térmica, fusible, borneras)
A40: 32 | B40: Tablero metálico dedicado a CCTV (mismas características, independiente del anterior)
A41: 33 | B41: Relay externo para accionamiento de sirenas desde PGM/BELL
A42: 34 | E42: 0 | F42: 0 | G42: =IF(F42=0,0,F42*$B$4*E42) -> 0 | H42: =IF(F42=0,0,G42*$D$5) -> 0 | I42: =IF(F42=0,0,G42+H42) -> 0 | J42: =$F$4 -> 0.46 | K42: =IF(F42=0,0,I42*$J$4) -> 0 | L42: =IF(F42=0,0,I42*(1+$J$7)+K42) -> 0 | M42: =IF(F42=0,0,L42*(1+$D$4)) -> 0 | N42: =IF(F42=0,0,L42-I42) -> 0
A43: 35 | B43: COSTO DE ENVÍO | C43: ENCOMIENDA | D43: Activo | E43: 1 | F43: 0 | G43: =IF(F43=0,0,F43*$B$4*E43) -> 0 | H43: 0 | I43: =IF(F43=0,0,G43+H43) -> 0 | J43: =$F$4 -> 0.46 | K43: 0 | L43: =IF(F43=0,0,I43*(1+$J$7)+K43) -> 0 | M43: =IF(F43=0,0,L43*(1+$D$4)) -> 0 | N43: =IF(F43=0,0,L43-I43) -> 0
B44: ▶ TOTALES DEL PROYECTO | F44: =SUM(F7:F43) -> 0 | G44: =SUM(G7:G43) -> 0 | H44: =SUM(H7:H43) -> 0 | I44: =SUM(I7:I43) -> 0 | J44: =F4 -> 0.46 | K44: =SUM(K7:K43) -> 0 | L44: =SUM(L7:L43) -> 0 | M44: =SUM(M7:M43) -> 0 | N44: =SUM(N7:N43) -> 0
G49: COSTOS ADICIONALES DEL PROYECTO
G50: MANO DE OBRA
G51: CANT. TÉCNICOS | H51: DÍAS HÁBILES | I51: CANT. HORAS (×8 hs/día) | J51: VALOR HORA USD | K51: TOTAL USD | L51: DÓLAR + IVA | M51: TOTAL PESOS | N51: PESOS + IVA
G52: 0 | H52: 0 | I52: =IF(G52*H52=0,0,G52*H52*8) -> 0 | J52: 15.125 | K52: =IF(I52*J52=0,0,I52*J52) -> 0 | L52: =IF(K52=0,0,K52*(1+$D$4)) -> 0 | M52: =IF(K52=0,0,K52*$B$4) -> 0 | N52: =IF(M52=0,0,M52*(1+$D$4)) -> 0
G53: 0 | H53: 0 | I53: =IF(G53*H53=0,0,G53*H53*8) -> 0 | J53: 15.125 | K53: =IF(I53*J53=0,0,I53*J53) -> 0 | L53: =IF(K53=0,0,K53*(1+$D$4)) -> 0 | M53: =IF(K53=0,0,K53*$B$4) -> 0 | N53: =IF(M53=0,0,M53*(1+$D$4)) -> 0
G54: 0 | H54: 0 | I54: =IF(G54*H54=0,0,G54*H54*8) -> 0 | J54: 15.125 | K54: =IF(I54*J54=0,0,I54*J54) -> 0 | L54: =IF(K54=0,0,K54*(1+$D$4)) -> 0 | M54: =IF(K54=0,0,K54*$B$4) -> 0 | N54: =IF(M54=0,0,M54*(1+$D$4)) -> 0
G55: TOTAL MANO DE OBRA | K55: =SUM(K52:K54) -> 0 | L55: =SUM(L52:L54) -> 0 | M55: =SUM(M52:M54) -> 0 | N55: =SUM(N52:N54) -> 0
G57: KILÓMETROS / TRASLADOS
G58: KMS (ida) | H58: KMS (regreso) | I58: CANT. KMS (kms × 2) | J58: VALOR KM USD | K58: TOTAL USD | L58: DÓLAR + IVA | M58: TOTAL PESOS | N58: PESOS + IVA
G59: 0 | H59: =G59 -> 0 | I59: =IF(G59*2=0,0,G59*2) -> 0 | J59: 1.331 | K59: =IF(I59*J59=0,0,I59*J59) -> 0 | L59: =IF(K59=0,0,K59*$B$4*(1+$D$4)) -> 0 | M59: =IF(K59=0,0,K59*$B$4) -> 0 | N59: =IF(M59=0,0,M59*(1+$D$4)) -> 0
G60: 0 | H60: =G60 -> 0 | I60: =IF(G60*2=0,0,G60*2) -> 0 | J60: 1.331 | K60: =IF(I60*J60=0,0,I60*J60) -> 0 | L60: =IF(K60=0,0,K60*$B$4*(1+$D$4)) -> 0 | M60: =IF(K60=0,0,K60*$B$4) -> 0 | N60: =IF(M60=0,0,M60*(1+$D$4)) -> 0
G61: 0 | H61: =G61 -> 0 | I61: =IF(G61*2=0,0,G61*2) -> 0 | J61: 1.331 | K61: =IF(I61*J61=0,0,I61*J61) -> 0 | L61: =IF(K61=0,0,K61*$B$4*(1+$D$4)) -> 0 | M61: =IF(K61=0,0,K61*$B$4) -> 0 | N61: =IF(M61=0,0,M61*(1+$D$4)) -> 0
G62: TOTAL KILÓMETROS | K62: =SUM(K59:K61) -> 0 | L62: =SUM(L59:L61) -> 0 | M62: =SUM(M59:M61) -> 0 | N62: =SUM(N59:N61) -> 0
A66: COSTO PROYECTO FINAL
A67: PROYECTO
A68: N° | B68: DESCRIPCIÓN | C68: P. VENTA SIN IVA | D68: P. VENTA CON IVA
A69: 1 | B69: PRODUCTOS / SERVICIO | C69: =L44 -> 0 | D69: =M44 -> 0
A70: 2 | B70: MANO DE OBRA | C70: =M55 -> 0 | D70: =N55 -> 0
A71: 3 | B71: KILÓMETROS / TRASLADOS | C71: =M62 -> 0 | D71: =N62 -> 0
A72: TOTAL | C72: =SUM(C69:C71) -> 0 | D72: =SUM(D69:D71) -> 0

Sheet mantenimiento
A1: GESTIÓN DE PROYECTOS DE VENTA · Argentina
A2: Actualizado: 21/05/2026 | 🔵 Inputs en azul | ⚫ Fórmulas en negro | 🟢 Resultados clave | MK variable — recomendado 46%
A3: ⚙ PARÁMETROS — Argentina 2025
A4: DÓLAR | B4: 1550 | C4: IVA (%) | D4: 0.21 | E4: MK (%) | F4: 0.46 | G4: MK MÍNIMO (%) | H4: 0.3 | I4: COMISIÓN (%) | J4: 0.05
A5: INFLACIÓN ANUAL | B5: 0.3 | C5: IMPREVISTOS (%) | D5: 0.1 | E5: CUOTA VARIABLE (Meses) | F5: 12 | G5: CANT. AÑOS PROY. | H5: 0 | I5: COMODATO %
A6: N° | B6: PRODUCTO / SERVICIO | C6: PROVEEDOR | D6: ESTADO | E6: CANT. | F6: COSTO USD | G6: COSTO ARS | H6: IMPREVISTOS | I6: COSTO REAL SIN IVA | J6: MK (%) | K6: COMISIÓN | L6: P. VENTA SIN IVA | M6: P. VENTA CON IVA | N6: UTILIDAD ARS
A7: 1 | B7: INSUMOS MENORES | E7: 1 | F7: 50 | G7: =IF(F7=0,0,F7*$B$4*E7) -> 77500 | H7: =IF(F7=0,0,G7*$D$5) -> 7750 | I7: =IF(F7=0,0,G7+H7) -> 85250 | J7: =$F$4 -> 0.46 | K7: =IF(F7=0,0,I7*$J$4) -> 4262.5 | L7: =IF(F7=0,0,I7*(1+$J$7)+K7) -> 128727.5 | M7: =IF(F7=0,0,L7*(1+$D$4)) -> 155760.27 | N7: =IF(F7=0,0,L7-I7) -> 43477.5
A8: 2 | E8: 0 | F8: 0 | G8: =IF(F8=0,0,F8*$B$4*E8) -> 0 | H8: =IF(F8=0,0,G8*$D$5) -> 0 | I8: =IF(F8=0,0,G8+H8) -> 0 | J8: =$F$4 -> 0.46 | K8: =IF(F8=0,0,I8*$J$4) -> 0 | L8: =IF(F8=0,0,I8*(1+$J$7)+K8) -> 0 | M8: =IF(F8=0,0,L8*(1+$D$4)) -> 0 | N8: =IF(F8=0,0,L8-I8) -> 0
B9: ▶ TOTALES DEL PROYECTO | F9: =SUM(F7:F8) -> 50 | G9: =SUM(G7:G8) -> 77500 | H9: =SUM(H7:H8) -> 7750 | I9: =SUM(I7:I8) -> 85250 | J9: =F4 -> 0.46 | K9: =SUM(K7:K8) -> 4262.5 | L9: =SUM(L7:L8) -> 128727.5 | M9: =SUM(M7:M8) -> 155760.27 | N9: =SUM(N7:N8) -> 43477.5
G14: COSTOS ADICIONALES DEL PROYECTO
G15: MANO DE OBRA
G16: CANT. TÉCNICOS | H16: DÍAS HÁBILES | I16: CANT. HORAS (×8 hs/día) | J16: VALOR HORA USD | K16: TOTAL USD | L16: DÓLAR + IVA | M16: TOTAL PESOS | N16: PESOS + IVA
G17: 2 | H17: 1 | I17: =IF(G17*H17=0,0,G17*H17*8) -> 16 | J17: 12.5 | K17: =IF(I17*J17=0,0,I17*J17) -> 200 | L17: =IF(K17=0,0,K17*(1+$D$4)) -> 242 | M17: =IF(K17=0,0,K17*$B$4) -> 310000 | N17: =IF(M17=0,0,M17*(1+$D$4)) -> 375100
G18: 0 | H18: 0 | I18: =IF(G18*H18=0,0,G18*H18*8) -> 0 | J18: 15.125 | K18: =IF(I18*J18=0,0,I18*J18) -> 0 | L18: =IF(K18=0,0,K18*(1+$D$4)) -> 0 | M18: =IF(K18=0,0,K18*$B$4) -> 0 | N18: =IF(M18=0,0,M18*(1+$D$4)) -> 0
G19: 0 | H19: 0 | I19: =IF(G19*H19=0,0,G19*H19*8) -> 0 | J19: 15.125 | K19: =IF(I19*J19=0,0,I19*J19) -> 0 | L19: =IF(K19=0,0,K19*(1+$D$4)) -> 0 | M19: =IF(K19=0,0,K19*$B$4) -> 0 | N19: =IF(M19=0,0,M19*(1+$D$4)) -> 0
G20: TOTAL MANO DE OBRA | K20: =SUM(K17:K19) -> 200 | L20: =SUM(L17:L19) -> 242 | M20: =SUM(M17:M19) -> 310000 | N20: =SUM(N17:N19) -> 375100
G22: KILÓMETROS / TRASLADOS
G23: KMS (ida) | H23: KMS (regreso) | I23: CANT. KMS (kms × 2) | J23: VALOR KM USD | K23: TOTAL USD | L23: DÓLAR + IVA | M23: TOTAL PESOS | N23: PESOS + IVA
G24: 0 | H24: =G24 -> 0 | I24: =IF(G24*2=0,0,G24*2) -> 0 | J24: 1.331 | K24: =IF(I24*J24=0,0,I24*J24) -> 0 | L24: =IF(K24=0,0,K24*$B$4*(1+$D$4)) -> 0 | M24: =IF(K24=0,0,K24*$B$4) -> 0 | N24: =IF(M24=0,0,M24*(1+$D$4)) -> 0
G25: 0 | H25: =G25 -> 0 | I25: =IF(G25*2=0,0,G25*2) -> 0 | J25: 1.331 | K25: =IF(I25*J25=0,0,I25*J25) -> 0 | L25: =IF(K25=0,0,K25*$B$4*(1+$D$4)) -> 0 | M25: =IF(K25=0,0,K25*$B$4) -> 0 | N25: =IF(M25=0,0,M25*(1+$D$4)) -> 0
G26: 0 | H26: =G26 -> 0 | I26: =IF(G26*2=0,0,G26*2) -> 0 | J26: 1.331 | K26: =IF(I26*J26=0,0,I26*J26) -> 0 | L26: =IF(K26=0,0,K26*$B$4*(1+$D$4)) -> 0 | M26: =IF(K26=0,0,K26*$B$4) -> 0 | N26: =IF(M26=0,0,M26*(1+$D$4)) -> 0
G27: TOTAL KILÓMETROS | K27: =SUM(K24:K26) -> 0 | L27: =SUM(L24:L26) -> 0 | M27: =SUM(M24:M26) -> 0 | N27: =SUM(N24:N26) -> 0
A31: COSTO PROYECTO FINAL
A32: PROYECTO
A33: N° | B33: DESCRIPCIÓN | C33: P. VENTA SIN IVA | D33: P. VENTA CON IVA
A34: 1 | B34: PRODUCTOS / SERVICIO | C34: =L9 -> 128727.5 | D34: =M9 -> 155760.27
A35: 2 | B35: MANO DE OBRA | C35: =M20 -> 310000 | D35: =N20 -> 375100
A36: 3 | B36: KILÓMETROS / TRASLADOS | C36: =M27 -> 0 | D36: =N27 -> 0
A37: TOTAL | C37: =SUM(C34:C36) -> 438727.5 | D37: =SUM(D34:D36) -> 530860.28

Sheet DEALTEC
A1: GESTIÓN DE PROYECTOS DE VENTA · Argentina
A2: Actualizado: 21/05/2026 | 🔵 Inputs en azul | ⚫ Fórmulas en negro | 🟢 Resultados clave | MK variable — recomendado 46%
A3: ⚙ PARÁMETROS — Argentina 2025
A4: DÓLAR | B4: 1550 | C4: IVA (%) | D4: 0.21 | E4: MK (%) | F4: 0.46 | G4: MK MÍNIMO (%) | H4: 0.3 | I4: COMISIÓN (%) | J4: 0.05
A5: INFLACIÓN ANUAL | B5: 0.3 | C5: IMPREVISTOS (%) | D5: 0.1 | E5: CUOTA VARIABLE (Meses) | F5: 12 | G5: CANT. AÑOS PROY. | H5: 0 | I5: COMODATO %
A6: N° | B6: PRODUCTO / SERVICIO | C6: PROVEEDOR | D6: ESTADO | E6: CANT. | F6: COSTO USD | G6: COSTO ARS | H6: IMPREVISTOS | I6: COSTO REAL SIN IVA | J6: MK (%) | K6: COMISIÓN | L6: P. VENTA SIN IVA | M6: P. VENTA CON IVA | N6: UTILIDAD ARS
B7: SISTEMA DE ALARMA | D7: Cancelado
B8: (HS2032-HS2ICN) DSC Neo Central de 8 zonas c/teclado HS2ICN | C8: DEALTEC | D8: Cancelado | E8: 0 | F8: 116.16 | G8: =IF(F8=0,0,F8*$B$4*E8) -> 0 | H8: =IF(F8=0,0,G8*$D$5) -> 0 | I8: =IF(F8=0,0,G8+H8) -> 0 | J8: =$F$4 -> 0.46 | K8: =IF(F8=0,0,I8*$J$4) -> 0 | L8: =IF(F8=0,0,I8*(1+$J$7)+K8) -> 0 | M8: =IF(F8=0,0,L8*(1+$D$4)) -> 0 | N8: =IF(F8=0,0,L8-I8) -> 0
B9: (PC5003C) DSC Gabinete Expansor Grande PowerSeries | C9: DEALTEC | D9: Cancelado | E9: 0 | F9: 43.82 | G9: =IF(F9=0,0,F9*$B$4*E9) -> 0 | H9: =IF(F9=0,0,G9*$D$5) -> 0 | I9: =IF(F9=0,0,G9+H9) -> 0 | J9: =$F$4 -> 0.46 | K9: =IF(F9=0,0,I9*$J$4) -> 0 | L9: =IF(F9=0,0,I9*(1+$J$7)+K9) -> 0 | M9: =IF(F9=0,0,L9*(1+$D$4)) -> 0 | N9: =IF(F9=0,0,L9-I9) -> 0
B10: Gabinete para fuente de alimentación de sirenas | D10: Cancelado | E10: 0 | F10: 0 | G10: =IF(F10=0,0,F10*$B$4*E10) -> 0 | H10: =IF(F10=0,0,G10*$D$5) -> 0 | I10: =IF(F10=0,0,G10+H10) -> 0 | J10: =$F$4 -> 0.46 | K10: =IF(F10=0,0,I10*$J$4) -> 0 | L10: =IF(F10=0,0,I10*(1+$J$7)+K10) -> 0 | M10: =IF(F10=0,0,L10*(1+$D$4)) -> 0 | N10: =IF(F10=0,0,L10-I10) -> 0
B11: (HSM2204) DSC Neo Módulo de salida de alta corriente | C11: DEALTEC | D11: Cancelado | E11: 0 | F11: 111.12 | G11: =IF(F11=0,0,F11*$B$4*E11) -> 0 | H11: =IF(F11=0,0,G11*$D$5) -> 0 | I11: =IF(F11=0,0,G11+H11) -> 0 | J11: =$F$4 -> 0.46 | K11: =IF(F11=0,0,I11*$J$4) -> 0 | L11: =IF(F11=0,0,I11*(1+$J$7)+K11) -> 0 | M11: =IF(F11=0,0,L11*(1+$D$4)) -> 0 | N11: =IF(F11=0,0,L11-I11) -> 0
B12: (HSM2108) Modulo Expansor de 8 zonas DSC - Unidades | C12: DEALTEC | D12: Cancelado | E12: 0 | F12: 37.04 | G12: =IF(F12=0,0,F12*$B$4*E12) -> 0 | H12: =IF(F12=0,0,G12*$D$5) -> 0 | I12: =IF(F12=0,0,G12+H12) -> 0 | J12: =$F$4 -> 0.46 | K12: =IF(F12=0,0,I12*$J$4) -> 0 | L12: =IF(F12=0,0,I12*(1+$J$7)+K12) -> 0 | M12: =IF(F12=0,0,L12*(1+$D$4)) -> 0 | N12: =IF(F12=0,0,L12-I12) -> 0
B13: (TRA-ALARMA) Transformador para Alarmas DSC | C13: DEALTEC | D13: Cancelado | E13: 0 | F13: 12.69 | G13: =IF(F13=0,0,F13*$B$4*E13) -> 0 | H13: =IF(F13=0,0,G13*$D$5) -> 0 | I13: =IF(F13=0,0,G13+H13) -> 0 | J13: =$F$4 -> 0.46 | K13: =IF(F13=0,0,I13*$J$4) -> 0 | L13: =IF(F13=0,0,I13*(1+$J$7)+K13) -> 0 | M13: =IF(F13=0,0,L13*(1+$D$4)) -> 0 | N13: =IF(F13=0,0,L13-I13) -> 0
B14: (LC-104-PIMW-WNL) DSC Detector de Doble Tecnología Digital | C14: DEALTEC | D14: Cancelado | E14: 0 | F14: 32.27 | G14: =IF(F14=0,0,F14*$B$4*E14) -> 0 | H14: =IF(F14=0,0,G14*$D$5) -> 0 | I14: =IF(F14=0,0,G14+H14) -> 0 | J14: =$F$4 -> 0.46 | K14: =IF(F14=0,0,I14*$J$4) -> 0 | L14: =IF(F14=0,0,I14*(1+$J$7)+K14) -> 0 | M14: =IF(F14=0,0,L14*(1+$D$4)) -> 0 | N14: =IF(F14=0,0,L14-I14) -> 0
B15: (PG9922) Detector inalámbrico de rotura de vidrio Power G | C15: DEALTEC | D15: Cancelado | E15: 0 | F15: 78.44 | G15: =IF(F15=0,0,F15*$B$4*E15) -> 0 | H15: =IF(F15=0,0,G15*$D$5) -> 0 | I15: =IF(F15=0,0,G15+H15) -> 0 | J15: =$F$4 -> 0.46 | K15: =IF(F15=0,0,I15*$J$4) -> 0 | L15: =IF(F15=0,0,I15*(1+$J$7)+K15) -> 0 | M15: =IF(F15=0,0,L15*(1+$D$4)) -> 0 | N15: =IF(F15=0,0,L15-I15) -> 0
B16: PG9303) Contacto magnetico ultradelgado color blanco | C16: DEALTEC | D16: Cancelado | E16: 0 | F16: 34.88 | G16: =IF(F16=0,0,F16*$B$4*E16) -> 0 | H16: =IF(F16=0,0,G16*$D$5) -> 0 | I16: =IF(F16=0,0,G16+H16) -> 0 | J16: =$F$4 -> 0.46 | K16: =IF(F16=0,0,I16*$J$4) -> 0 | L16: =IF(F16=0,0,I16*(1+$J$7)+K16) -> 0 | M16: =IF(F16=0,0,L16*(1+$D$4)) -> 0 | N16: =IF(F16=0,0,L16-I16) -> 0
B17: (PG9939) Llavero de 4 canales programables | C17: DEALTEC | D17: Cancelado | E17: 0 | F17: 43.61 | G17: =IF(F17=0,0,F17*$B$4*E17) -> 0 | H17: =IF(F17=0,0,G17*$D$5) -> 0 | I17: =IF(F17=0,0,G17+H17) -> 0 | J17: =$F$4 -> 0.46 | K17: =IF(F17=0,0,I17*$J$4) -> 0 | L17: =IF(F17=0,0,I17*(1+$J$7)+K17) -> 0 | M17: =IF(F17=0,0,L17*(1+$D$4)) -> 0 | N17: =IF(F17=0,0,L17-I17) -> 0
B18: (GN-BKP127) Bateria Keypower 12V 7A | C18: DEALTEC | D18: Cancelado | E18: 0 | F18: 12.15 | G18: =IF(F18=0,0,F18*$B$4*E18) -> 0 | H18: =IF(F18=0,0,G18*$D$5) -> 0 | I18: =IF(F18=0,0,G18+H18) -> 0 | J18: =$F$4 -> 0.46 | K18: =IF(F18=0,0,I18*$J$4) -> 0 | L18: =IF(F18=0,0,I18*(1+$J$7)+K18) -> 0 | M18: =IF(F18=0,0,L18*(1+$D$4)) -> 0 | N18: =IF(F18=0,0,L18-I18) -> 0
B19: (HSM2HOST9) Transceptor inalámbrico bidireccional power G | C19: DEALTEC | D19: Cancelado | E19: 0 | F19: 124.77 | G19: =IF(F19=0,0,F19*$B$4*E19) -> 0 | H19: =IF(F19=0,0,G19*$D$5) -> 0 | I19: =IF(F19=0,0,G19+H19) -> 0 | J19: =$F$4 -> 0.46 | K19: =IF(F19=0,0,I19*$J$4) -> 0 | L19: =IF(F19=0,0,I19*(1+$J$7)+K19) -> 0 | M19: =IF(F19=0,0,L19*(1+$D$4)) -> 0 | N19: =IF(F19=0,0,L19-I19) -> 0
B20: SISTEMA DE INCENDIO | D20: Cancelado | E20: 0
B21: (DS-PDSMK-4) Hikvision Detector de Humo Cableado (4 Hilos) | C21: DEALTEC | D21: Cancelado | E21: 0 | F21: 13.6 | G21: =IF(F21=0,0,F21*$B$4*E21) -> 0 | H21: =IF(F21=0,0,G21*$D$5) -> 0 | I21: =IF(F21=0,0,G21+H21) -> 0 | J21: =$F$4 -> 0.46 | K21: =IF(F21=0,0,I21*$J$4) -> 0 | L21: =IF(F21=0,0,I21*(1+$J$7)+K21) -> 0 | M21: =IF(F21=0,0,L21*(1+$D$4)) -> 0 | N21: =IF(F21=0,0,L21-I21) -> 0
B22: (DT-4323-4AR) Sensor de temperatura 4 hilos | C22: DEALTEC | D22: Cancelado | E22: 0 | F22: 17.82 | G22: =IF(F22=0,0,F22*$B$4*E22) -> 0 | H22: =IF(F22=0,0,G22*$D$5) -> 0 | I22: =IF(F22=0,0,G22+H22) -> 0 | J22: =$F$4 -> 0.46 | K22: =IF(F22=0,0,I22*$J$4) -> 0 | L22: =IF(F22=0,0,I22*(1+$J$7)+K22) -> 0 | M22: =IF(F22=0,0,L22*(1+$D$4)) -> 0 | N22: =IF(F22=0,0,L22-I22) -> 0
B23: (AV-M103D) Avisador manual de doble acción | C23: DEALTEC | D23: Cancelado | E23: 0 | F23: 30.29 | G23: =IF(F23=0,0,F23*$B$4*E23) -> 0 | H23: =IF(F23=0,0,G23*$D$5) -> 0 | I23: =IF(F23=0,0,G23+H23) -> 0 | J23: =$F$4 -> 0.46 | K23: =IF(F23=0,0,I23*$J$4) -> 0 | L23: =IF(F23=0,0,I23*(1+$J$7)+K23) -> 0 | M23: =IF(F23=0,0,L23*(1+$D$4)) -> 0 | N23: =IF(F23=0,0,L23-I23) -> 0
B24: (FA-411-24) Sirena de Incendio Interior con Strobo Dlux | C24: DEALTEC | D24: Cancelado | E24: 0 | F24: 14.04 | G24: =IF(F24=0,0,F24*$B$4*E24) -> 0 | H24: =IF(F24=0,0,G24*$D$5) -> 0 | I24: =IF(F24=0,0,G24+H24) -> 0 | J24: =$F$4 -> 0.46 | K24: =IF(F24=0,0,I24*$J$4) -> 0 | L24: =IF(F24=0,0,I24*(1+$J$7)+K24) -> 0 | M24: =IF(F24=0,0,L24*(1+$D$4)) -> 0 | N24: =IF(F24=0,0,L24-I24) -> 0
B25: SIRENA | D25: Cancelado | E25: 0 | F25: 0 | G25: =IF(F25=0,0,F25*$B$4*E25) -> 0 | H25: =IF(F25=0,0,G25*$D$5) -> 0 | I25: =IF(F25=0,0,G25+H25) -> 0 | J25: =$F$4 -> 0.46 | K25: =IF(F25=0,0,I25*$J$4) -> 0 | L25: =IF(F25=0,0,I25*(1+$J$7)+K25) -> 0 | M25: =IF(F25=0,0,L25*(1+$D$4)) -> 0 | N25: =IF(F25=0,0,L25-I25) -> 0
B26: (SD-100) Sirena Piezoeléctrica Bitonal Interior con Tamper | C26: DEALTEC | D26: Cancelado | E26: 0 | F26: 5.45 | G26: =IF(F26=0,0,F26*$B$4*E26) -> 0 | H26: =IF(F26=0,0,G26*$D$5) -> 0 | I26: =IF(F26=0,0,G26+H26) -> 0 | J26: =$F$4 -> 0.46 | K26: =IF(F26=0,0,I26*$J$4) -> 0 | L26: =IF(F26=0,0,I26*(1+$J$7)+K26) -> 0 | M26: =IF(F26=0,0,L26*(1+$D$4)) -> 0 | N26: =IF(F26=0,0,L26-I26) -> 0
B27: (SD-1150MD) Dumont Sirena Exterior con Flash | C27: DEALTEC | D27: Cancelado | E27: 0 | F27: 29.4 | G27: =IF(F27=0,0,F27*$B$4*E27) -> 0 | H27: =IF(F27=0,0,G27*$D$5) -> 0 | I27: =IF(F27=0,0,G27+H27) -> 0 | J27: =$F$4 -> 0.46 | K27: =IF(F27=0,0,I27*$J$4) -> 0 | L27: =IF(F27=0,0,I27*(1+$J$7)+K27) -> 0 | M27: =IF(F27=0,0,L27*(1+$D$4)) -> 0 | N27: =IF(F27=0,0,L27-I27) -> 0
B28: COMUNICACION | D28: Cancelado | E28: 0 | F28: 0 | G28: =IF(F28=0,0,F28*$B$4*E28) -> 0 | H28: =IF(F28=0,0,G28*$D$5) -> 0 | I28: =IF(F28=0,0,G28+H28) -> 0 | J28: =$F$4 -> 0.46 | K28: =IF(F28=0,0,I28*$J$4) -> 0 | L28: =IF(F28=0,0,I28*(1+$J$7)+K28) -> 0 | M28: =IF(F28=0,0,L28*(1+$D$4)) -> 0 | N28: =IF(F28=0,0,L28-I28) -> 0
B29: (TL280LE-LAT) DSC Comunicador celular de doble vínculo | C29: DEALTEC | D29: Cancelado | E29: 0 | F29: 159.84 | G29: =IF(F29=0,0,F29*$B$4*E29) -> 0 | H29: =IF(F29=0,0,G29*$D$5) -> 0 | I29: =IF(F29=0,0,G29+H29) -> 0 | J29: =$F$4 -> 0.46 | K29: =IF(F29=0,0,I29*$J$4) -> 0 | L29: =IF(F29=0,0,I29*(1+$J$7)+K29) -> 0 | M29: =IF(F29=0,0,L29*(1+$D$4)) -> 0 | N29: =IF(F29=0,0,L29-I29) -> 0
B30: Licencia/habilitación App Connect Alarm | D30: Cancelado | E30: 0 | F30: 0 | G30: =IF(F30=0,0,F30*$B$4*E30) -> 0 | H30: =IF(F30=0,0,G30*$D$5) -> 0 | I30: =IF(F30=0,0,G30+H30) -> 0 | J30: =$F$4 -> 0.46 | K30: =IF(F30=0,0,I30*$J$4) -> 0 | L30: =IF(F30=0,0,I30*(1+$J$7)+K30) -> 0 | M30: =IF(F30=0,0,L30*(1+$D$4)) -> 0 | N30: =IF(F30=0,0,L30-I30) -> 0
B31: SISTEMA DE CCTV
B32: (DS-7608NXI-K2/8P(D)) Hikvision NVR de 8 Canales POE 4K | C32: DEALTEC | D32: Aprobado | E32: 1 | F32: 524 | G32: =IF(F32=0,0,F32*$B$4*E32) -> 812200 | H32: =IF(F32=0,0,G32*$D$5) -> 81220 | I32: =IF(F32=0,0,G32+H32) -> 893420 | J32: =$F$4 -> 0.46 | K32: =IF(F32=0,0,I32*$J$4) -> 44671 | L32: =IF(F32=0,0,I32*(1+$J$7)+K32) -> 938091 | M32: =IF(F32=0,0,L32*(1+$D$4)) -> 1135090.1 | N32: =IF(F32=0,0,L32-I32) -> 44671
B33: (WD-HDD6000P) Wester Digital HDD Sata3 6TB Purple | C33: DEALTEC | D33: Aprobado | E33: 1 | F33: 310.47 | G33: =IF(F33=0,0,F33*$B$4*E33) -> 481228.5 | H33: =IF(F33=0,0,G33*$D$5) -> 48122.85 | I33: =IF(F33=0,0,G33+H33) -> 529351.35 | J33: =$F$4 -> 0.46 | K33: =IF(F33=0,0,I33*$J$4) -> 26467.568 | L33: =IF(F33=0,0,I33*(1+$J$7)+K33) -> 555818.92 | M33: =IF(F33=0,0,L33*(1+$D$4)) -> 672540.89 | N33: =IF(F33=0,0,L33-I33) -> 26467.568
B34: (GLC-BAND-FIJA-001) GLC Bandeja Fija de 1 Unidad 300mm | C34: DEALTEC | D34: Aprobado | E34: 1 | F34: 15.32 | G34: =IF(F34=0,0,F34*$B$4*E34) -> 23746 | H34: =IF(F34=0,0,G34*$D$5) -> 2374.6 | I34: =IF(F34=0,0,G34+H34) -> 26120.6 | J34: =$F$4 -> 0.46 | K34: =IF(F34=0,0,I34*$J$4) -> 1306.03 | L34: =IF(F34=0,0,I34*(1+$J$7)+K34) -> 27426.63 | M34: =IF(F34=0,0,L34*(1+$D$4)) -> 33186.222 | N34: =IF(F34=0,0,L34-I34) -> 1306.03
B35: (DS-2CD1343G2-LIUF) Hikvision Cámara IP Domo 4Mpx con Audio | C35: DEALTEC | D35: Aprobado | E35: 3 | F35: 93 | G35: =IF(F35=0,0,F35*$B$4*E35) -> 432450 | H35: =IF(F35=0,0,G35*$D$5) -> 43245 | I35: =IF(F35=0,0,G35+H35) -> 475695 | J35: =$F$4 -> 0.46 | K35: =IF(F35=0,0,I35*$J$4) -> 23784.75 | L35: =IF(F35=0,0,I35*(1+$J$7)+K35) -> 499479.75 | M35: =IF(F35=0,0,L35*(1+$D$4)) -> 604370.5 | N35: =IF(F35=0,0,L35-I35) -> 23784.75
B36: (DS-2CD1043G2-LIUF) Hikvision Cámara IP Bullet 4Mpx con Audio | C36: DEALTEC | D36: Aprobado | E36: 4 | F36: 93 | G36: =IF(F36=0,0,F36*$B$4*E36) -> 576600 | H36: =IF(F36=0,0,G36*$D$5) -> 57660 | I36: =IF(F36=0,0,G36+H36) -> 634260 | J36: =$F$4 -> 0.46 | K36: =IF(F36=0,0,I36*$J$4) -> 31713 | L36: =IF(F36=0,0,I36*(1+$J$7)+K36) -> 665973 | M36: =IF(F36=0,0,L36*(1+$D$4)) -> 805827.33 | N36: =IF(F36=0,0,L36-I36) -> 31713
B37: (XL600-CPR-B) ZKTeco Cable UTP Cat. 6 305mts 100% Cobre EXTERIOR | C37: DEALTEC | D37: En Revisión | E37: 2 | F37: 187.65 | G37: =IF(F37=0,0,F37*$B$4*E37) -> 581715 | H37: =IF(F37=0,0,G37*$D$5) -> 58171.5 | I37: =IF(F37=0,0,G37+H37) -> 639886.5 | J37: =$F$4 -> 0.46 | K37: =IF(F37=0,0,I37*$J$4) -> 31994.325 | L37: =IF(F37=0,0,I37*(1+$J$7)+K37) -> 671880.82 | M37: =IF(F37=0,0,L37*(1+$D$4)) -> 812975.8 | N37: =IF(F37=0,0,L37-I37) -> 31994.325
B38: Conectores RJ45 y accesorios de terminación | C38: vario | E38: 1 | F38: 100 | G38: =IF(F38=0,0,F38*$B$4*E38) -> 155000 | H38: =IF(F38=0,0,G38*$D$5) -> 15500 | I38: =IF(F38=0,0,G38+H38) -> 170500 | J38: =$F$4 -> 0.46 | K38: =IF(F38=0,0,I38*$J$4) -> 8525 | L38: =IF(F38=0,0,I38*(1+$J$7)+K38) -> 179025 | M38: =IF(F38=0,0,L38*(1+$D$4)) -> 216620.25 | N38: =IF(F38=0,0,L38-I38) -> 8525
B39: ALIMENTACION Y TABLEROS
B40: Tablero metálico dedicado a Intrusión/Incendio (con disyuntor, térmica, fusible, borneras) | E40: 0 | F40: 0 | G40: =IF(F40=0,0,F40*$B$4*E40) -> 0 | H40: =IF(F40=0,0,G40*$D$5) -> 0 | I40: =IF(F40=0,0,G40+H40) -> 0 | J40: =$F$4 -> 0.46 | K40: =IF(F40=0,0,I40*$J$4) -> 0 | L40: =IF(F40=0,0,I40*(1+$J$7)+K40) -> 0 | M40: =IF(F40=0,0,L40*(1+$D$4)) -> 0 | N40: =IF(F40=0,0,L40-I40) -> 0
B41: Tablero metálico dedicado a CCTV (mismas características, independiente del anterior) | E41: 0 | F41: 0 | G41: =IF(F41=0,0,F41*$B$4*E41) -> 0 | H41: =IF(F41=0,0,G41*$D$5) -> 0 | I41: =IF(F41=0,0,G41+H41) -> 0 | J41: =$F$4 -> 0.46 | K41: =IF(F41=0,0,I41*$J$4) -> 0 | L41: =IF(F41=0,0,I41*(1+$J$7)+K41) -> 0 | M41: =IF(F41=0,0,L41*(1+$D$4)) -> 0 | N41: =IF(F41=0,0,L41-I41) -> 0
B42: Relay externo para accionamiento de sirenas desde PGM/BELL | E42: 0 | F42: 0 | G42: =IF(F42=0,0,F42*$B$4*E42) -> 0 | H42: =IF(F42=0,0,G42*$D$5) -> 0 | I42: =IF(F42=0,0,G42+H42) -> 0 | J42: =$F$4 -> 0.46 | K42: =IF(F42=0,0,I42*$J$4) -> 0 | L42: =IF(F42=0,0,I42*(1+$J$7)+K42) -> 0 | M42: =IF(F42=0,0,L42*(1+$D$4)) -> 0 | N42: =IF(F42=0,0,L42-I42) -> 0
B44: COSTO DE ENVÍO | C44: ENCOMIENDA | D44: Activo | E44: 1 | F44: 50 | G44: =IF(F44=0,0,F44*$B$4*E44) -> 77500 | H44: 0 | I44: =IF(F44=0,0,G44+H44) -> 77500 | J44: =$F$4 -> 0.46 | K44: 0 | L44: =IF(F44=0,0,I44*(1+$J$7)+K44) -> 77500 | M44: =IF(F44=0,0,L44*(1+$D$4)) -> 93775 | N44: =IF(F44=0,0,L44-I44) -> 0
B45: ▶ TOTALES DEL PROYECTO | F45: =SUM(F7:F44) -> 2290.83 | G45: =SUM(G7:G44) -> 3140439.5 | H45: =SUM(H7:H44) -> 306293.95 | I45: =SUM(I7:I44) -> 3446733.5 | J45: =F4 -> 0.46 | K45: =SUM(K7:K44) -> 168461.67 | L45: =SUM(L7:L44) -> 3615195.1 | M45: =SUM(M7:M44) -> 4374386.1 | N45: =SUM(N7:N44) -> 168461.67
G50: COSTOS ADICIONALES DEL PROYECTO
G51: MANO DE OBRA
G52: CANT. TÉCNICOS | H52: DÍAS HÁBILES | I52: CANT. HORAS (×8 hs/día) | J52: VALOR HORA USD | K52: TOTAL USD | L52: DÓLAR + IVA | M52: TOTAL PESOS | N52: PESOS + IVA
G53: 0 | H53: 0 | I53: =IF(G53*H53=0,0,G53*H53*8) -> 0 | J53: 15.125 | K53: =IF(I53*J53=0,0,I53*J53) -> 0 | L53: =IF(K53=0,0,K53*(1+$D$4)) -> 0 | M53: =IF(K53=0,0,K53*$B$4) -> 0 | N53: =IF(M53=0,0,M53*(1+$D$4)) -> 0
G54: 0 | H54: 0 | I54: =IF(G54*H54=0,0,G54*H54*8) -> 0 | J54: 15.125 | K54: =IF(I54*J54=0,0,I54*J54) -> 0 | L54: =IF(K54=0,0,K54*(1+$D$4)) -> 0 | M54: =IF(K54=0,0,K54*$B$4) -> 0 | N54: =IF(M54=0,0,M54*(1+$D$4)) -> 0
G55: 0 | H55: 0 | I55: =IF(G55*H55=0,0,G55*H55*8) -> 0 | J55: 15.125 | K55: =IF(I55*J55=0,0,I55*J55) -> 0 | L55: =IF(K55=0,0,K55*(1+$D$4)) -> 0 | M55: =IF(K55=0,0,K55*$B$4) -> 0 | N55: =IF(M55=0,0,M55*(1+$D$4)) -> 0
G56: TOTAL MANO DE OBRA | K56: =SUM(K53:K55) -> 0 | L56: =SUM(L53:L55) -> 0 | M56: =SUM(M53:M55) -> 0 | N56: =SUM(N53:N55) -> 0
G58: KILÓMETROS / TRASLADOS
G59: KMS (ida) | H59: KMS (regreso) | I59: CANT. KMS (kms × 2) | J59: VALOR KM USD | K59: TOTAL USD | L59: DÓLAR + IVA | M59: TOTAL PESOS | N59: PESOS + IVA
G60: 0 | H60: =G60 -> 0 | I60: =IF(G60*2=0,0,G60*2) -> 0 | J60: 1.331 | K60: =IF(I60*J60=0,0,I60*J60) -> 0 | L60: =IF(K60=0,0,K60*$B$4*(1+$D$4)) -> 0 | M60: =IF(K60=0,0,K60*$B$4) -> 0 | N60: =IF(M60=0,0,M60*(1+$D$4)) -> 0
G61: 0 | H61: =G61 -> 0 | I61: =IF(G61*2=0,0,G61*2) -> 0 | J61: 1.331 | K61: =IF(I61*J61=0,0,I61*J61) -> 0 | L61: =IF(K61=0,0,K61*$B$4*(1+$D$4)) -> 0 | M61: =IF(K61=0,0,K61*$B$4) -> 0 | N61: =IF(M61=0,0,M61*(1+$D$4)) -> 0
G62: 0 | H62: =G62 -> 0 | I62: =IF(G62*2=0,0,G62*2) -> 0 | J62: 1.331 | K62: =IF(I62*J62=0,0,I62*J62) -> 0 | L62: =IF(K62=0,0,K62*$B$4*(1+$D$4)) -> 0 | M62: =IF(K62=0,0,K62*$B$4) -> 0 | N62: =IF(M62=0,0,M62*(1+$D$4)) -> 0
G63: TOTAL KILÓMETROS | K63: =SUM(K60:K62) -> 0 | L63: =SUM(L60:L62) -> 0 | M63: =SUM(M60:M62) -> 0 | N63: =SUM(N60:N62) -> 0
A67: COSTO PROYECTO FINAL
A68: PROYECTO
A69: N° | B69: DESCRIPCIÓN | C69: P. VENTA SIN IVA | D69: P. VENTA CON IVA
A70: 1 | B70: PRODUCTOS / SERVICIO | C70: =L45 -> 3615195.1 | D70: =M45 -> 4374386.1
A71: 2 | B71: MANO DE OBRA | C71: =M56 -> 0 | D71: =N56 -> 0
A72: 3 | B72: KILÓMETROS / TRASLADOS | C72: =M63 -> 0 | D72: =N63 -> 0
A73: TOTAL | C73: =SUM(C70:C72) -> 3615195.1 | D73: =SUM(D70:D72) -> 4374386.1

Sheet DMA
A1: GESTIÓN DE PROYECTOS DE VENTA · Argentina
A2: Actualizado: 21/05/2026 | 🔵 Inputs en azul | ⚫ Fórmulas en negro | 🟢 Resultados clave | MK variable — recomendado 46%
A3: ⚙ PARÁMETROS — Argentina 2025
A4: DÓLAR | B4: 1550 | C4: IVA (%) | D4: 0.21 | E4: MK (%) | F4: 0.46 | G4: MK MÍNIMO (%) | H4: 0.3 | I4: COMISIÓN (%) | J4: 0.05
A5: INFLACIÓN ANUAL | B5: 0.3 | C5: IMPREVISTOS (%) | D5: 0.1 | E5: CUOTA VARIABLE (Meses) | F5: 12 | G5: CANT. AÑOS PROY. | H5: 0 | I5: COMODATO %
A6: N° | B6: PRODUCTO / SERVICIO | C6: PROVEEDOR | D6: ESTADO | E6: CANT. | F6: COSTO USD | G6: COSTO ARS | H6: IMPREVISTOS | I6: COSTO REAL SIN IVA | J6: MK (%) | K6: COMISIÓN | L6: P. VENTA SIN IVA | M6: P. VENTA CON IVA | N6: UTILIDAD ARS
B7: SISTEMA DE ALARMA
A8: 3 modelos de panel para seleccionar | B8: HS2032PCBARG PANEL 8 ZONAS EXPANDIBLE A 32 NEO | C8: DMA | J8: 0
B9: HS2064PCB HS2064PCBCH PANEL 8 Z EXP A 64Z NEO | C9: DMA | D9: Aprobado | E9: 1 | F9: 59.3 | G9: =IF(F9=0,0,F9*$B$4*E9) -> 91915 | H9: =IF(F9=0,0,G9*$D$5) -> 9191.5 | I9: =IF(F9=0,0,G9+H9) -> 101106.5 | J9: =$F$4 -> 0.46 | K9: =IF(F9=0,0,I9*$J$4) -> 5055.325 | L9: =IF(F9=0,0,I9*(1+$J$7)+K9) -> 106161.82 | M9: =IF(F9=0,0,L9*(1+$D$4)) -> 128455.81 | N9: =IF(F9=0,0,L9-I9) -> 5055.325
B10: 2128PCBARG PANEL 8 ZONAS EXP A 128ZONAS NEO | C10: DMA | J10: 0
B11: DSC, GAB METAL G3 POWERSERIES PRO 45.9x41.4x10.3cm | C11: DMA | E11: 1 | F11: 50.92 | G11: =IF(F11=0,0,F11*$B$4*E11) -> 78926 | H11: =IF(F11=0,0,G11*$D$5) -> 7892.6 | I11: =IF(F11=0,0,G11+H11) -> 86818.6 | J11: =$F$4 -> 0.46 | K11: =IF(F11=0,0,I11*$J$4) -> 4340.93 | L11: =IF(F11=0,0,I11*(1+$J$7)+K11) -> 91159.53 | M11: =IF(F11=0,0,L11*(1+$D$4)) -> 110303.03 | N11: =IF(F11=0,0,L11-I11) -> 4340.93
B12: HS2LCD N TECLADO ALFANUMERICO LCD POWER NEO | C12: DMA | D12: Aprobado | E12: 2 | F12: 82 | G12: =IF(F12=0,0,F12*$B$4*E12) -> 254200 | H12: =IF(F12=0,0,G12*$D$5) -> 25420 | I12: =IF(F12=0,0,G12+H12) -> 279620 | J12: =$F$4 -> 0.46 | K12: =IF(F12=0,0,I12*$J$4) -> 13981 | L12: =IF(F12=0,0,I12*(1+$J$7)+K12) -> 293601 | M12: =IF(F12=0,0,L12*(1+$D$4)) -> 355257.21 | N12: =IF(F12=0,0,L12-I12) -> 13981
B13: HSM2204 FUENTE DE ALIMENTACION C/4 SALIDAS NEO | C13: DMA | E13: 1 | F13: 89 | G13: =IF(F13=0,0,F13*$B$4*E13) -> 137950 | H13: =IF(F13=0,0,G13*$D$5) -> 13795 | I13: =IF(F13=0,0,G13+H13) -> 151745 | J13: =$F$4 -> 0.46 | K13: =IF(F13=0,0,I13*$J$4) -> 7587.25 | L13: =IF(F13=0,0,I13*(1+$J$7)+K13) -> 159332.25 | M13: =IF(F13=0,0,L13*(1+$D$4)) -> 192792.02 | N13: =IF(F13=0,0,L13-I13) -> 7587.25
B14: HSM2108 EXPANSOR DE 8 ZONAS POWER NEO | C14: DMA | D14: Aprobado | E14: 4 | F14: 38.2 | G14: =IF(F14=0,0,F14*$B$4*E14) -> 236840 | H14: =IF(F14=0,0,G14*$D$5) -> 23684 | I14: =IF(F14=0,0,G14+H14) -> 260524 | J14: =$F$4 -> 0.46 | K14: =IF(F14=0,0,I14*$J$4) -> 13026.2 | L14: =IF(F14=0,0,I14*(1+$J$7)+K14) -> 273550.2 | M14: =IF(F14=0,0,L14*(1+$D$4)) -> 330995.74 | N14: =IF(F14=0,0,L14-I14) -> 13026.2
B15: HSM2300 FUENTE DE ALIMENTACION NEO | C15: DMA | E15: 1 | F15: 61.4 | G15: =IF(F15=0,0,F15*$B$4*E15) -> 95170 | H15: =IF(F15=0,0,G15*$D$5) -> 9517 | I15: =IF(F15=0,0,G15+H15) -> 104687 | J15: =$F$4 -> 0.46 | K15: =IF(F15=0,0,I15*$J$4) -> 5234.35 | L15: =IF(F15=0,0,I15*(1+$J$7)+K15) -> 109921.35 | M15: =IF(F15=0,0,L15*(1+$D$4)) -> 133004.83 | N15: =IF(F15=0,0,L15-I15) -> 5234.35
B16: LC-204 DETECTOR PIR DOBLE TECH MASC 15KGS | C16: DMA | D16: Aprobado | E16: 10 | F16: 42 | G16: =IF(F16=0,0,F16*$B$4*E16) -> 651000 | H16: =IF(F16=0,0,G16*$D$5) -> 65100 | I16: =IF(F16=0,0,G16+H16) -> 716100 | J16: =$F$4 -> 0.46 | K16: =IF(F16=0,0,I16*$J$4) -> 35805 | L16: =IF(F16=0,0,I16*(1+$J$7)+K16) -> 751905 | M16: =IF(F16=0,0,L16*(1+$D$4)) -> 909805.05 | N16: =IF(F16=0,0,L16-I16) -> 35805
B17: PG9922 DETECTOR ROTURA DE VIDRIOS WLS NEO | C17: DMA | E17: ? | F17: 53.4 | G17: =IF(F17=0,0,F17*$B$4*E17) -> #VALUE! | H17: =IF(F17=0,0,G17*$D$5) -> #VALUE! | I17: =IF(F17=0,0,G17+H17) -> #VALUE! | J17: =$F$4 -> 0.46 | K17: =IF(F17=0,0,I17*$J$4) -> #VALUE! | L17: =IF(F17=0,0,I17*(1+$J$7)+K17) -> #VALUE! | M17: =IF(F17=0,0,L17*(1+$D$4)) -> #VALUE! | N17: =IF(F17=0,0,L17-I17) -> #VALUE!
B18: PG9945 CONTACTO MAGNETICO COMUN NEO | C18: DMA | D18: Aprobado | E18: 5 | F18: 35.9 | G18: =IF(F18=0,0,F18*$B$4*E18) -> 278225 | H18: =IF(F18=0,0,G18*$D$5) -> 27822.5 | I18: =IF(F18=0,0,G18+H18) -> 306047.5 | J18: =$F$4 -> 0.46 | K18: =IF(F18=0,0,I18*$J$4) -> 15302.375 | L18: =IF(F18=0,0,I18*(1+$J$7)+K18) -> 321349.88 | M18: =IF(F18=0,0,L18*(1+$D$4)) -> 388833.35 | N18: =IF(F18=0,0,L18-I18) -> 15302.375
B19: PG9929 CONTROL REMOTO 4 BOTONES NEO | C19: DMA | D19: Aprobado | E19: 3 | F19: 35.5 | G19: =IF(F19=0,0,F19*$B$4*E19) -> 165075 | H19: =IF(F19=0,0,G19*$D$5) -> 16507.5 | I19: =IF(F19=0,0,G19+H19) -> 181582.5 | J19: =$F$4 -> 0.46 | K19: =IF(F19=0,0,I19*$J$4) -> 9079.125 | L19: =IF(F19=0,0,I19*(1+$J$7)+K19) -> 190661.62 | M19: =IF(F19=0,0,L19*(1+$D$4)) -> 230700.57 | N19: =IF(F19=0,0,L19-I19) -> 9079.125
B20: PW7-12 BATERIA - POWER-PLUS 12V 7 AMPERES | C20: DMA | E20: 1 | F20: 12.15 | G20: =IF(F20=0,0,F20*$B$4*E20) -> 18832.5 | H20: =IF(F20=0,0,G20*$D$5) -> 1883.25 | I20: =IF(F20=0,0,G20+H20) -> 20715.75 | J20: =$F$4 -> 0.46 | K20: =IF(F20=0,0,I20*$J$4) -> 1035.7875 | L20: =IF(F20=0,0,I20*(1+$J$7)+K20) -> 21751.537 | M20: =IF(F20=0,0,L20*(1+$D$4)) -> 26319.36 | N20: =IF(F20=0,0,L20-I20) -> 1035.7875
B21: SM2HOST9 TRANSCEPTOR WLSS P/ NEO | C21: DMA | E21: 1 | F21: 98 | G21: =IF(F21=0,0,F21*$B$4*E21) -> 151900 | H21: =IF(F21=0,0,G21*$D$5) -> 15190 | I21: =IF(F21=0,0,G21+H21) -> 167090 | J21: =$F$4 -> 0.46 | K21: =IF(F21=0,0,I21*$J$4) -> 8354.5 | L21: =IF(F21=0,0,I21*(1+$J$7)+K21) -> 175444.5 | M21: =IF(F21=0,0,L21*(1+$D$4)) -> 212287.85 | N21: =IF(F21=0,0,L21-I21) -> 8354.5
B22: SISTEMA DE INCENDIO | E22: 0 | F22: 0
B23: HY-C134-CTXF DETECTOR DE HUMO FOTOELECTRICO 4 HILO - DAHUA | C23: DMA | D23: Aprobado | E23: 13 | F23: 14.7 | G23: =IF(F23=0,0,F23*$B$4*E23) -> 296205 | H23: =IF(F23=0,0,G23*$D$5) -> 29620.5 | I23: =IF(F23=0,0,G23+H23) -> 325825.5 | J23: =$F$4 -> 0.46 | K23: =IF(F23=0,0,I23*$J$4) -> 16291.275 | L23: =IF(F23=0,0,I23*(1+$J$7)+K23) -> 342116.78 | M23: =IF(F23=0,0,L23*(1+$D$4)) -> 413961.3 | N23: =IF(F23=0,0,L23-I23) -> 16291.275
B24: HY-C136-CTXF DETECTOR DE TEMPERATURA 4 HILOS - 12V - DAHUA | C24: DMA | D24: Aprobado | E24: 1 | F24: 13.7 | G24: =IF(F24=0,0,F24*$B$4*E24) -> 21235 | H24: =IF(F24=0,0,G24*$D$5) -> 2123.5 | I24: =IF(F24=0,0,G24+H24) -> 23358.5 | J24: =$F$4 -> 0.46 | K24: =IF(F24=0,0,I24*$J$4) -> 1167.925 | L24: =IF(F24=0,0,I24*(1+$J$7)+K24) -> 24526.425 | M24: =IF(F24=0,0,L24*(1+$D$4)) -> 29676.974 | N24: =IF(F24=0,0,L24-I24) -> 1167.925
B25: HY-C121 ESTACION MANUAL CONVENCIONAL 2 HILOS C/BAS - DAHUA | C25: DMA | D25: Aprobado | E25: 3 | F25: 11.5 | G25: =IF(F25=0,0,F25*$B$4*E25) -> 53475 | H25: =IF(F25=0,0,G25*$D$5) -> 5347.5 | I25: =IF(F25=0,0,G25+H25) -> 58822.5 | J25: =$F$4 -> 0.46 | K25: =IF(F25=0,0,I25*$J$4) -> 2941.125 | L25: =IF(F25=0,0,I25*(1+$J$7)+K25) -> 61763.625 | M25: =IF(F25=0,0,L25*(1+$D$4)) -> 74733.986 | N25: =IF(F25=0,0,L25-I25) -> 2941.125
B26: HY-C151 SIRENA CON STROBO CONVENCIONAL 2 HILOS C/B - DAHUA | C26: DMA | D26: Aprobado | E26: 3 | F26: 24.1 | G26: =IF(F26=0,0,F26*$B$4*E26) -> 112065 | H26: =IF(F26=0,0,G26*$D$5) -> 11206.5 | I26: =IF(F26=0,0,G26+H26) -> 123271.5 | J26: =$F$4 -> 0.46 | K26: =IF(F26=0,0,I26*$J$4) -> 6163.575 | L26: =IF(F26=0,0,I26*(1+$J$7)+K26) -> 129435.07 | M26: =IF(F26=0,0,L26*(1+$D$4)) -> 156616.44 | N26: =IF(F26=0,0,L26-I26) -> 6163.575
B27: SIRENA | E27: 0 | F27: 0 | G27: =IF(F27=0,0,F27*$B$4*E27) -> 0 | H27: =IF(F27=0,0,G27*$D$5) -> 0 | I27: =IF(F27=0,0,G27+H27) -> 0 | J27: =$F$4 -> 0.46 | K27: =IF(F27=0,0,I27*$J$4) -> 0 | L27: =IF(F27=0,0,I27*(1+$J$7)+K27) -> 0 | M27: =IF(F27=0,0,L27*(1+$D$4)) -> 0 | N27: =IF(F27=0,0,L27-I27) -> 0
B28: MP100 SIRENA INT PIEZO 1 TONO - ALONZO | C28: DMA | E28: ? | F28: 9.1 | G28: =IF(F28=0,0,F28*$B$4*E28) -> #VALUE! | H28: =IF(F28=0,0,G28*$D$5) -> #VALUE! | I28: =IF(F28=0,0,G28+H28) -> #VALUE! | J28: =$F$4 -> 0.46 | K28: =IF(F28=0,0,I28*$J$4) -> #VALUE! | L28: =IF(F28=0,0,I28*(1+$J$7)+K28) -> #VALUE! | M28: =IF(F28=0,0,L28*(1+$D$4)) -> #VALUE! | N28: =IF(F28=0,0,L28-I28) -> #VALUE!
B29: SIR-300T SIRENA EXTERIOR PARLANTE C/FLASH 3 TONOS - DMAX | C29: DMA | D29: Aprobado | E29: 1 | F29: 42.9 | G29: =IF(F29=0,0,F29*$B$4*E29) -> 66495 | H29: =IF(F29=0,0,G29*$D$5) -> 6649.5 | I29: =IF(F29=0,0,G29+H29) -> 73144.5 | J29: =$F$4 -> 0.46 | K29: =IF(F29=0,0,I29*$J$4) -> 3657.225 | L29: =IF(F29=0,0,I29*(1+$J$7)+K29) -> 76801.725 | M29: =IF(F29=0,0,L29*(1+$D$4)) -> 92930.087 | N29: =IF(F29=0,0,L29-I29) -> 3657.225
B30: COMUNICACION | E30: 0 | F30: 0 | G30: =IF(F30=0,0,F30*$B$4*E30) -> 0 | H30: =IF(F30=0,0,G30*$D$5) -> 0 | I30: =IF(F30=0,0,G30+H30) -> 0 | J30: =$F$4 -> 0.46 | K30: =IF(F30=0,0,I30*$J$4) -> 0 | L30: =IF(F30=0,0,I30*(1+$J$7)+K30) -> 0 | M30: =IF(F30=0,0,L30*(1+$D$4)) -> 0 | N30: =IF(F30=0,0,L30-I30) -> 0
B31: TL2803GE-LAT COMUNICADOR INTERNET/3G SERIE NEO | C31: DMA | D31: Aprobado | E31: 1 | F31: 129.9 | G31: =IF(F31=0,0,F31*$B$4*E31) -> 201345 | H31: =IF(F31=0,0,G31*$D$5) -> 20134.5 | I31: =IF(F31=0,0,G31+H31) -> 221479.5 | J31: =$F$4 -> 0.46 | K31: =IF(F31=0,0,I31*$J$4) -> 11073.975 | L31: =IF(F31=0,0,I31*(1+$J$7)+K31) -> 232553.48 | M31: =IF(F31=0,0,L31*(1+$D$4)) -> 281389.7 | N31: =IF(F31=0,0,L31-I31) -> 11073.975
B32: Licencia/habilitación App Connect Alarm | E32: 0 | F32: 0 | G32: =IF(F32=0,0,F32*$B$4*E32) -> 0 | H32: =IF(F32=0,0,G32*$D$5) -> 0 | I32: =IF(F32=0,0,G32+H32) -> 0 | J32: =$F$4 -> 0.46 | K32: =IF(F32=0,0,I32*$J$4) -> 0 | L32: =IF(F32=0,0,I32*(1+$J$7)+K32) -> 0 | M32: =IF(F32=0,0,L32*(1+$D$4)) -> 0 | N32: =IF(F32=0,0,L32-I32) -> 0
B33: SISTEMA DE CCTV | E33: 0 | F33: 0
B34: NVR4108HS-8P-4KS3 NVR 8 CH 1HDD 8 POE 4K - DAHUA | C34: DMA | D34: Cancelado | E34: 0 | F34: 339.96 | G34: =IF(F34=0,0,F34*$B$4*E34) -> 0 | H34: =IF(F34=0,0,G34*$D$5) -> 0 | I34: =IF(F34=0,0,G34+H34) -> 0 | J34: =$F$4 -> 0.46 | K34: =IF(F34=0,0,I34*$J$4) -> 0 | L34: =IF(F34=0,0,I34*(1+$J$7)+K34) -> 0 | M34: =IF(F34=0,0,L34*(1+$D$4)) -> 0 | N34: =IF(F34=0,0,L34-I34) -> 0
B35: 2TB-WD-B DISCO 2TB WD BLUE | C35: DMA | D35: Cancelado | E35: 0 | F35: 163 | G35: =IF(F35=0,0,F35*$B$4*E35) -> 0 | H35: =IF(F35=0,0,G35*$D$5) -> 0 | I35: =IF(F35=0,0,G35+H35) -> 0 | J35: =$F$4 -> 0.46 | K35: =IF(F35=0,0,I35*$J$4) -> 0 | L35: =IF(F35=0,0,I35*(1+$J$7)+K35) -> 0 | M35: =IF(F35=0,0,L35*(1+$D$4)) -> 0 | N35: =IF(F35=0,0,L35-I35) -> 0
B36: PFC610-4D RACK MOUNT TRAY | C36: DMA | D36: Cancelado | E36: 0 | F36: 15.56 | G36: =IF(F36=0,0,F36*$B$4*E36) -> 0 | H36: =IF(F36=0,0,G36*$D$5) -> 0 | I36: =IF(F36=0,0,G36+H36) -> 0 | J36: =$F$4 -> 0.46 | K36: =IF(F36=0,0,I36*$J$4) -> 0 | L36: =IF(F36=0,0,I36*(1+$J$7)+K36) -> 0 | M36: =IF(F36=0,0,L36*(1+$D$4)) -> 0 | N36: =IF(F36=0,0,L36-I36) -> 0
B37: IPC-HDW1431T1-0280B DOMO IP 4MP LENTE 2.8mm - DAHUA | C37: DMA | D37: Cancelado | E37: 0 | F37: 73.86 | G37: =IF(F37=0,0,F37*$B$4*E37) -> 0 | H37: =IF(F37=0,0,G37*$D$5) -> 0 | I37: =IF(F37=0,0,G37+H37) -> 0 | J37: =$F$4 -> 0.46 | K37: =IF(F37=0,0,I37*$J$4) -> 0 | L37: =IF(F37=0,0,I37*(1+$J$7)+K37) -> 0 | M37: =IF(F37=0,0,L37*(1+$D$4)) -> 0 | N37: =IF(F37=0,0,L37-I37) -> 0
B38: IPC-HFW1439TL1P-A-IL-0280BS6 BULLET IP 4MP LENTE 2 - DAHUA | C38: DMA | D38: Cancelado | E38: 0 | F38: 81.46 | G38: =IF(F38=0,0,F38*$B$4*E38) -> 0 | H38: =IF(F38=0,0,G38*$D$5) -> 0 | I38: =IF(F38=0,0,G38+H38) -> 0 | J38: =$F$4 -> 0.46 | K38: =IF(F38=0,0,I38*$J$4) -> 0 | L38: =IF(F38=0,0,I38*(1+$J$7)+K38) -> 0 | M38: =IF(F38=0,0,L38*(1+$D$4)) -> 0 | N38: =IF(F38=0,0,L38-I38) -> 0
B39: CS4220-16GT-240 SWITCH 20 IN 10/100 16 POE+ 240 WA - DAHUA | C39: DMA | D39: Cancelado | E39: 0 | F39: 234.97 | G39: =IF(F39=0,0,F39*$B$4*E39) -> 0 | H39: =IF(F39=0,0,G39*$D$5) -> 0 | I39: =IF(F39=0,0,G39+H39) -> 0 | J39: =$F$4 -> 0.46 | K39: =IF(F39=0,0,I39*$J$4) -> 0 | L39: =IF(F39=0,0,I39*(1+$J$7)+K39) -> 0 | M39: =IF(F39=0,0,L39*(1+$D$4)) -> 0 | N39: =IF(F39=0,0,L39-I39) -> 0
B40: PFM920I-6UN-CN-BLANCO CABLE UTP CAT6 INT 305MT - DAHUA | C40: DMA | D40: Cancelado | E40: 0 | F40: 199 | G40: =IF(F40=0,0,F40*$B$4*E40) -> 0 | H40: =IF(F40=0,0,G40*$D$5) -> 0 | I40: =IF(F40=0,0,G40+H40) -> 0 | J40: =$F$4 -> 0.46 | K40: =IF(F40=0,0,I40*$J$4) -> 0 | L40: =IF(F40=0,0,I40*(1+$J$7)+K40) -> 0 | M40: =IF(F40=0,0,L40*(1+$D$4)) -> 0 | N40: =IF(F40=0,0,L40-I40) -> 0
B41: PFM976-631 CONECTOR RJ45 CAT6 CAJA x 100 PCS | C41: DMA | D41: Cancelado | E41: 0 | F41: 9 | G41: =IF(F41=0,0,F41*$B$4*E41) -> 0 | H41: =IF(F41=0,0,G41*$D$5) -> 0 | I41: =IF(F41=0,0,G41+H41) -> 0 | J41: =$F$4 -> 0.46 | K41: =IF(F41=0,0,I41*$J$4) -> 0 | L41: =IF(F41=0,0,I41*(1+$J$7)+K41) -> 0 | M41: =IF(F41=0,0,L41*(1+$D$4)) -> 0 | N41: =IF(F41=0,0,L41-I41) -> 0
B42: Accesorios Y MAS | D42: Aprobado | E42: 1 | F42: 100 | G42: =IF(F42=0,0,F42*$B$4*E42) -> 155000 | H42: =IF(F42=0,0,G42*$D$5) -> 15500 | I42: =IF(F42=0,0,G42+H42) -> 170500 | J42: =$F$4 -> 0.46 | K42: =IF(F42=0,0,I42*$J$4) -> 8525 | L42: =IF(F42=0,0,I42*(1+$J$7)+K42) -> 179025 | M42: =IF(F42=0,0,L42*(1+$D$4)) -> 216620.25 | N42: =IF(F42=0,0,L42-I42) -> 8525
B43: ALIMENTACION Y TABLEROS | E43: 0 | F43: 0
B44: Tablero metálico dedicado a Intrusión/Incendio (con disyuntor, térmica, fusible, borneras) | E44: 0 | F44: 0 | G44: =IF(F44=0,0,F44*$B$4*E44) -> 0 | H44: =IF(F44=0,0,G44*$D$5) -> 0 | I44: =IF(F44=0,0,G44+H44) -> 0 | J44: =$F$4 -> 0.46 | K44: =IF(F44=0,0,I44*$J$4) -> 0 | L44: =IF(F44=0,0,I44*(1+$J$7)+K44) -> 0 | M44: =IF(F44=0,0,L44*(1+$D$4)) -> 0 | N44: =IF(F44=0,0,L44-I44) -> 0
B45: Tablero metálico dedicado a CCTV (mismas características, independiente del anterior) | E45: 0 | F45: 0 | G45: =IF(F45=0,0,F45*$B$4*E45) -> 0 | H45: =IF(F45=0,0,G45*$D$5) -> 0 | I45: =IF(F45=0,0,G45+H45) -> 0 | J45: =$F$4 -> 0.46 | K45: =IF(F45=0,0,I45*$J$4) -> 0 | L45: =IF(F45=0,0,I45*(1+$J$7)+K45) -> 0 | M45: =IF(F45=0,0,L45*(1+$D$4)) -> 0 | N45: =IF(F45=0,0,L45-I45) -> 0
B46: Relay externo para accionamiento de sirenas desde PGM/BELL | E46: 0 | F46: 0 | G46: =IF(F46=0,0,F46*$B$4*E46) -> 0 | H46: =IF(F46=0,0,G46*$D$5) -> 0 | I46: =IF(F46=0,0,G46+H46) -> 0 | J46: =$F$4 -> 0.46 | K46: =IF(F46=0,0,I46*$J$4) -> 0 | L46: =IF(F46=0,0,I46*(1+$J$7)+K46) -> 0 | M46: =IF(F46=0,0,L46*(1+$D$4)) -> 0 | N46: =IF(F46=0,0,L46-I46) -> 0
B48: COSTO DE ENVÍO | C48: ENCOMIENDA | D48: Activo | E48: 1 | F48: 50 | G48: =IF(F48=0,0,F48*$B$4*E48) -> 77500 | H48: 0 | I48: =IF(F48=0,0,G48+H48) -> 77500 | J48: =$F$4 -> 0.46 | K48: 0 | L48: =IF(F48=0,0,I48*(1+$J$7)+K48) -> 77500 | M48: =IF(F48=0,0,L48*(1+$D$4)) -> 93775 | N48: =IF(F48=0,0,L48-I48) -> 0
B49: ▶ TOTALES DEL PROYECTO | F49: =SUM(F7:F48) -> 2170.48 | G49: =SUM(G7:G48) -> #VALUE! | H49: =SUM(H7:H48) -> #VALUE! | I49: =SUM(I7:I48) -> #VALUE! | J49: =F4 -> 0.46 | K49: =SUM(K7:K48) -> #VALUE! | L49: =SUM(L7:L48) -> #VALUE! | M49: =SUM(M7:M48) -> #VALUE! | N49: =SUM(N7:N48) -> #VALUE!
G54: COSTOS ADICIONALES DEL PROYECTO
G55: MANO DE OBRA
G56: CANT. TÉCNICOS | H56: DÍAS HÁBILES | I56: CANT. HORAS (×8 hs/día) | J56: VALOR HORA USD | K56: TOTAL USD | L56: DÓLAR + IVA | M56: TOTAL PESOS | N56: PESOS + IVA
G57: 0 | H57: 0 | I57: =IF(G57*H57=0,0,G57*H57*8) -> 0 | J57: 15.125 | K57: =IF(I57*J57=0,0,I57*J57) -> 0 | L57: =IF(K57=0,0,K57*(1+$D$4)) -> 0 | M57: =IF(K57=0,0,K57*$B$4) -> 0 | N57: =IF(M57=0,0,M57*(1+$D$4)) -> 0
G58: 0 | H58: 0 | I58: =IF(G58*H58=0,0,G58*H58*8) -> 0 | J58: 15.125 | K58: =IF(I58*J58=0,0,I58*J58) -> 0 | L58: =IF(K58=0,0,K58*(1+$D$4)) -> 0 | M58: =IF(K58=0,0,K58*$B$4) -> 0 | N58: =IF(M58=0,0,M58*(1+$D$4)) -> 0
G59: 0 | H59: 0 | I59: =IF(G59*H59=0,0,G59*H59*8) -> 0 | J59: 15.125 | K59: =IF(I59*J59=0,0,I59*J59) -> 0 | L59: =IF(K59=0,0,K59*(1+$D$4)) -> 0 | M59: =IF(K59=0,0,K59*$B$4) -> 0 | N59: =IF(M59=0,0,M59*(1+$D$4)) -> 0
G60: TOTAL MANO DE OBRA | K60: =SUM(K57:K59) -> 0 | L60: =SUM(L57:L59) -> 0 | M60: =SUM(M57:M59) -> 0 | N60: =SUM(N57:N59) -> 0
G62: KILÓMETROS / TRASLADOS
G63: KMS (ida) | H63: KMS (regreso) | I63: CANT. KMS (kms × 2) | J63: VALOR KM USD | K63: TOTAL USD | L63: DÓLAR + IVA | M63: TOTAL PESOS | N63: PESOS + IVA
G64: 0 | H64: =G64 -> 0 | I64: =IF(G64*2=0,0,G64*2) -> 0 | J64: 1.331 | K64: =IF(I64*J64=0,0,I64*J64) -> 0 | L64: =IF(K64=0,0,K64*$B$4*(1+$D$4)) -> 0 | M64: =IF(K64=0,0,K64*$B$4) -> 0 | N64: =IF(M64=0,0,M64*(1+$D$4)) -> 0
G65: 0 | H65: =G65 -> 0 | I65: =IF(G65*2=0,0,G65*2) -> 0 | J65: 1.331 | K65: =IF(I65*J65=0,0,I65*J65) -> 0 | L65: =IF(K65=0,0,K65*$B$4*(1+$D$4)) -> 0 | M65: =IF(K65=0,0,K65*$B$4) -> 0 | N65: =IF(M65=0,0,M65*(1+$D$4)) -> 0
G66: 0 | H66: =G66 -> 0 | I66: =IF(G66*2=0,0,G66*2) -> 0 | J66: 1.331 | K66: =IF(I66*J66=0,0,I66*J66) -> 0 | L66: =IF(K66=0,0,K66*$B$4*(1+$D$4)) -> 0 | M66: =IF(K66=0,0,K66*$B$4) -> 0 | N66: =IF(M66=0,0,M66*(1+$D$4)) -> 0
G67: TOTAL KILÓMETROS | K67: =SUM(K64:K66) -> 0 | L67: =SUM(L64:L66) -> 0 | M67: =SUM(M64:M66) -> 0 | N67: =SUM(N64:N66) -> 0
A71: COSTO PROYECTO FINAL
A72: PROYECTO
A73: N° | B73: DESCRIPCIÓN | C73: P. VENTA SIN IVA | D73: P. VENTA CON IVA
A74: 1 | B74: PRODUCTOS / SERVICIO | C74: =L49 -> #VALUE! | D74: =M49 -> #VALUE!
A75: 2 | B75: MANO DE OBRA | C75: =M60 -> 0 | D75: =N60 -> 0
A76: 3 | B76: KILÓMETROS / TRASLADOS | C76: =M67 -> 0 | D76: =N67 -> 0
A77: TOTAL | C77: =SUM(C74:C76) -> #VALUE! | D77: =SUM(D74:D76) -> #VALUE!

Sheet Análisis Financiero
A1: 📊 ANÁLISIS FINANCIERO — Argentina 2025
A2: PARÁMETROS EN USO (fuente: hoja «Proyectos de Venta»)
A3: DÓLAR (ARS) | B3: ='Proyectos de Venta'!$B$4 -> 1550 | C3: Tipo de cambio oficial
A4: IVA (%) | B4: ='Proyectos de Venta'!$D$4 -> 0.21 | C4: IVA Argentina
A5: MK RECOMENDADO (%) | B5: ='Proyectos de Venta'!$F$4 -> 0.46 | C5: Estipulado por la empresa
A6: MK MÍNIMO (%) | B6: ='Proyectos de Venta'!$H$4 -> 0.3 | C6: Umbral de quiebre
A7: INFLACIÓN ANUAL | B7: ='Proyectos de Venta'!$B$5 -> 0.3 | C7: Estimación Argentina
A8: IMPREVISTOS (%) | B8: ='Proyectos de Venta'!$D$5 -> 0.1 | C8: Buffer riesgo cambiario
A9: CUOTA MESES | B9: ='Proyectos de Venta'!$F$5 -> 12 | C9: Plazo de financiación
A10: AÑOS PROYECTO | B10: ='Proyectos de Venta'!$H$5 -> 0 | C10: Horizonte de análisis
A12: 💰 KPIs TOTALES DEL PROYECTO
A13: KPI | B13: VALOR | D13: KPI | E13: VALOR | G13: KPI | H13: VALOR
A14: Total Costo USD | B14: ='Proyectos de Venta'!F44 -> 0 | D14: Total Costo ARS | E14: ='Proyectos de Venta'!G44 -> 0 | G14: Costo Real c/Imprevistos | H14: ='Proyectos de Venta'!I44 -> 0
A15: Total P. Venta c/IVA | B15: ='Proyectos de Venta'!M44 -> 0 | D15: Utilidad Total ARS | E15: ='Proyectos de Venta'!N44 -> 0 | G15: MK Promedio Ponderado | H15: ='Proyectos de Venta'!J44 -> 0.46
A19: 📅 PROYECCIÓN ANUAL CON INFLACIÓN & CUOTAS (contexto Argentina)
A20: AÑO | B20: P. VENTA PROYECTO (ARS s/IVA) | C20: FACTOR INFLACIÓN | D20: TOTAL INFLACIONADO | E20: CUOTA MENSUAL | F20: CUOTA CON IVA | G20: CUOTA EN USD | H20: ROI ESTIMADO
A21: VARIABLE | B21: ='Proyectos de Venta'!$C$72 -> 0 | C21: =POWER(1+'Proyectos de Venta'!$B$5,('Proyectos de Venta'!$F$5/12)) -> 1.3 | D21: =B21*C21 -> 0 | E21: =IFERROR(D21/'Proyectos de Venta'!$F$5,0) -> 0 | F21: =E21*(1+'Proyectos de Venta'!$D$4) -> 0 | G21: =IFERROR(E21/'Proyectos de Venta'!$B$4,0) -> 0 | H21: =IFERROR('Proyectos de Venta'!N44/('Proyectos de Venta'!I44*C21),0) -> 0
A22: Año 1 | B22: ='Proyectos de Venta'!$C$72 -> 0 | C22: =POWER(1+'Proyectos de Venta'!$B$5,1) -> 1.3 | D22: =B22*C22 -> 0 | E22: =IFERROR(D22/12,0) -> 0 | F22: =E22*(1+'Proyectos de Venta'!$D$4) -> 0 | G22: =IFERROR(E22/'Proyectos de Venta'!$B$4,0) -> 0 | H22: =IFERROR('Proyectos de Venta'!$N$44/('Proyectos de Venta'!$I$44*C22),0) -> 0
A23: Año 2 | B23: ='Proyectos de Venta'!$C$72 -> 0 | C23: =POWER(1+'Proyectos de Venta'!$B$5,2) -> 1.69 | D23: =B23*C23 -> 0 | E23: =IFERROR(D23/24,0) -> 0 | F23: =E23*(1+'Proyectos de Venta'!$D$4) -> 0 | G23: =IFERROR(E23/'Proyectos de Venta'!$B$4,0) -> 0 | H23: =IFERROR('Proyectos de Venta'!$N$44/('Proyectos de Venta'!$I$44*C23),0) -> 0
A24: Año 3 | B24: ='Proyectos de Venta'!$C$72 -> 0 | C24: =POWER(1+'Proyectos de Venta'!$B$5,3) -> 2.197 | D24: =B24*C24 -> 0 | E24: =IFERROR(D24/36,0) -> 0 | F24: =E24*(1+'Proyectos de Venta'!$D$4) -> 0 | G24: =IFERROR(E24/'Proyectos de Venta'!$B$4,0) -> 0 | H24: =IFERROR('Proyectos de Venta'!$N$44/('Proyectos de Venta'!$I$44*C24),0) -> 0
A27: 📌 CRITERIOS PARA ARGENTINA: • Dólar $1.420 ARS: Se recomienda usar dólar MEP o CCL para proyectos que impliquen costos en dólares reales. • IVA 21%: Estándar Argentina — verificar exenciones según rubro (servicios digitales, software exportado, etc.). • MK 46%: Estipulado por la empresa. Es variable por proyecto — el semáforo alerta si baja del 30% mínimo. • Imprevistos 8%: Colchón ampliado por volatilidad cambiaria y riesgo inflacionario. • Inflación ~50%: Para proyectos plurianuales se recomienda cotizar en dólares o ajustar precios semestralmente. • Horizonte 2 años: Dado el contexto macro, se desaconseja proyectar más de 2 años en pesos sin cláusula de ajuste.

Sheet Simulador MK
A1: 🔮 SIMULADOR DE ESCENARIOS MK — Argentina · IVA 21%
A2: Ingresá el Costo Real en ARS (sin IVA) en B4 y simulá el precio final y utilidad para distintos niveles de MK
A3: COSTO REAL (ARS sin IVA) | B3: 1000000 | C3: IVA (%) | D3: ='Proyectos de Venta'!$D$4 -> 0.21
A4: ESCENARIO | B4: MK (%) | C4: P. VENTA SIN IVA | D4: P. VENTA CON IVA | E4: UTILIDAD ARS | F4: % SOBRE COSTO | G4: EVALUACIÓN
A5: 🔴 Bajo mínimo empresa | B5: 0.25 | C5: =$B$3/(1-B5) -> 1333333.3 | D5: =C5*(1+$D$3) -> 1613333.3 | E5: =C5-$B$3 -> 333333.33 | F5: =E5/$B$3 -> 0.33333333 | G5: 🔴 Por debajo del mínimo — no operar
A6: 🔴 Mínimo empresa | B6: 0.3 | C6: =$B$3/(1-B6) -> 1428571.4 | D6: =C6*(1+$D$3) -> 1728571.4 | E6: =C6-$B$3 -> 428571.43 | F6: =E6/$B$3 -> 0.42857143 | G6: ⚠️ En el límite mínimo — riesgo alto
A7: 🟡 Conservador | B7: 0.35 | C7: =$B$3/(1-B7) -> 1538461.5 | D7: =C7*(1+$D$3) -> 1861538.5 | E7: =C7-$B$3 -> 538461.54 | F7: =E7/$B$3 -> 0.53846154 | G7: ✅ Viable — por debajo del objetivo empresa
A8: 🟡 Moderado | B8: 0.4 | C8: =$B$3/(1-B8) -> 1666666.7 | D8: =C8*(1+$D$3) -> 2016666.7 | E8: =C8-$B$3 -> 666666.67 | F8: =E8/$B$3 -> 0.66666667 | G8: ✅ Viable — por debajo del objetivo empresa
A9: ⭐ RECOMENDADO EMPRESA | B9: 0.46 | C9: =$B$3/(1-B9) -> 1851851.9 | D9: =C9*(1+$D$3) -> 2240740.7 | E9: =C9-$B$3 -> 851851.85 | F9: =E9/$B$3 -> 0.85185185 | G9: ✅ RECOMENDADO POR LA EMPRESA — MK estipulado 46%
A10: 🟢 Alto | B10: 0.5 | C10: =$B$3/(1-B10) -> 2000000 | D10: =C10*(1+$D$3) -> 2420000 | E10: =C10-$B$3 -> 1000000 | F10: =E10/$B$3 -> 1 | G10: 💎 Premium — justificar con propuesta de valor
A11: 💎 Premium | B11: 0.55 | C11: =$B$3/(1-B11) -> 2222222.2 | D11: =C11*(1+$D$3) -> 2688888.9 | E11: =C11-$B$3 -> 1222222.2 | F11: =E11/$B$3 -> 1.2222222 | G11: 💎 Premium — justificar con propuesta de valor
A12: ⚡ Alto Valor | B12: 0.6 | C12: =$B$3/(1-B12) -> 2500000 | D12: =C12*(1+$D$3) -> 3025000 | E12: =C12-$B$3 -> 1500000 | F12: =E12/$B$3 -> 1.5 | G12: 💎 Premium — justificar con propuesta de valor
